Workbook

Sheet Leia-me
A1: Planilha de gestão do MeasureSoftGram 2026.2
A2: Fonte de dados do Dashboard Analítico (aba Projeto). Cada aba abaixo é lida pelo app via "Publicar na web" em CSV. Definições completas em docs/metricas/modelo-de-gestao.mdx.
A4: Legenda
A5: Texto azul | B5: Dado de entrada, digitado pelo time.
A6: Fundo amarelo | B6: Entrada obrigatória ainda não preenchida.
A7: Fundo azul claro | B7: Coluna calculada por fórmula. Não editar.
A9: Abas
A10: Custos | B10: Modelo de custo com premissas e fontes (adaptado da planilha de 2026.1). Calcula custo por integrante/semana e custo/hora.
A11: Parametros | B11: Capacidade, custo/hora e regras do quadro, lidos pelo app. Capacidade e custo/hora vêm da aba Custos.
A12: Sprints | B12: Calendário oficial (o do Zenhub) e a release de cada sprint.
A13: Releases | B13: Data de entrega e linha de base de pontos (PRP) de cada release. Calcula horas planejadas e BAC.
A14: Horas | B14: Horas reais por integrante e sprint. Origem do custo real (AC). Uma linha por pessoa por sprint.
A15: Riscos | B15: Registro de riscos (PMBOK). Probabilidade e impacto de 1 a 5; exposição = P x I (1 a 25): 1-5 baixo, 6-12 médio, 15-25 elevado. Categorias EAR: Técnico, Gerencial, Organizacional, Externo.
A16: Decisoes | B16: Contexto e dado, decisão, evidência (PR, commit, doc), critério de sucesso e resultado. A R2 exige 3 registros e a R3 exige 5.
A17: Resumo | B17: Visão rápida calculada a partir das outras abas.
A18: Integrantes, Listas | B18: Listas usadas nos menus suspensos.
A20: Regras de preenchimento
A21: Cabeçalhos | B21: Não renomear nem mover as colunas da linha 1: o app lê pelo nome. Colunas novas podem ser acrescentadas no fim.
A22: Datas | B22: Formato aaaa-mm-dd (ex.: 2026-09-28).
A23: Horas | B23: Número, vírgula ou ponto como decimal. Exemplo de linha: sprint 4 | Milena Fernandes Rocha | 6,5 | pareamento no Parser
A24: PRP | B24: Congelado na planning de abertura da release: soma dos pontos das US/Tasks comprometidas. Não alterar depois; escopo novo entra como PA automaticamente.
A26: Rotina
A27: Toda segunda (planning) | B27: Cada integrante lança as horas da semana anterior na aba Horas.
A28: Abertura de release | B28: Preencher prp_linha_de_base em Releases.
A29: Toda retrospectiva | B29: Revisar Riscos (status, última revisão) e registrar Decisões.
A31: Publicar para o app
A32: Passo 1 | B32: Arquivo > Compartilhar > Publicar na web.
A33: Passo 2 | B33: Para cada aba lida pelo app (Parametros, Sprints, Releases, Horas, Riscos, Decisoes): escolher a aba e o formato CSV, clicar em Publicar e copiar o link.
A34: Passo 3 | B34: Colar cada link em Analytics/config.py, na chave de mesmo nome.

Sheet Resumo
A1: Resumo do projeto
A2: Calculado a partir das abas Custos, Releases, Horas, Riscos e Decisoes.
A4: Release | B4: Entrega | C4: PRP (pontos) | D4: Horas planejadas | E4: Horas reais | F4: % horas usadas
A5: =Releases!A2 | B5: =Releases!B2 | C5: =IF(Releases!C2="","sem linha de base",Releases!C2) | D5: =Releases!G2 | E5: =Releases!I2 | F5: =IF(OR(D5="",D5=0),"",E5/D5)
A6: =Releases!A3 | B6: =Releases!B3 | C6: =IF(Releases!C3="","sem linha de base",Releases!C3) | D6: =Releases!G3 | E6: =Releases!I3 | F6: =IF(OR(D6="",D6=0),"",E6/D6)
A7: =Releases!A4 | B7: =Releases!B4 | C7: =IF(Releases!C4="","sem linha de base",Releases!C4) | D7: =Releases!G4 | E7: =Releases!I4 | F7: =IF(OR(D7="",D7=0),"",E7/D7)
A9: Riscos | B9: Quantidade
A10: Abertos | B10: =COUNTIF(Riscos!O2:O1000,"Aberto")
A11: Em monitoramento | B11: =COUNTIF(Riscos!O2:O1000,"Em monitoramento")
A12: Materializados | B12: =COUNTIF(Riscos!O2:O1000,"Materializado")
A13: Encerrados | B13: =COUNTIF(Riscos!O2:O1000,"Encerrado")
A14: Exposição elevada (15 ou mais) | B14: =COUNTIF(Riscos!I2:I1000,">=15")
A15: Sem responsável | B15: =COUNTIFS(Riscos!A2:A1000,"<>",Riscos!N2:N1000,"")
A17: Horas | B17: Valor
A18: Total registrado | B18: =SUM(Horas!C2:C1000)
A19: Integrantes sem horas | B19: =COUNTIF(Integrantes!C2:C1000,0)
A20: Decisões registradas | B20: =COUNTA(Decisoes!A2:A1000)
A22: Custos | B22: Valor
A23: Custo por integrante/semana | B23: =Custos!B25
A24: Custo/hora | B24: =Parametros!B4
A25: Custo planejado R1 (BAC) | B25: =Releases!H2
A26: Custo planejado R2 (BAC) | B26: =Releases!H3
A27: Custo planejado R3 (BAC) | B27: =Releases!H4
A28: Custo planejado total | B28: =SUM(Releases!H2:H4)

Sheet Custos
A1: item | B1: valor | C1: unidade | D1: fonte
A2: Custo do aluno para a UnB
A3: custo_anual_aluno | B3: 52533 | C3: R$/ano | D3: Custo anual por aluno de universidade federal. Valor usado na planilha de custos do MeasureSoftGram 2026.1; atualizar se houver dado mais recente.
A4: creditos_ano | B4: 40 | C4: créditos/ano | D4: Carga anual média de créditos (planilha de custos 2026.1).
A5: custo_credito | B5: =B3/B4 | C5: R$/crédito | D5: custo_anual_aluno / creditos_ano
A6: creditos_eps | B6: 4 | C6: créditos | D6: EPS: 60 h, 4 créditos (plano de ensino).
A7: custo_eps | B7: =B5*B6 | C7: R$/semestre | D7: custo_credito x creditos_eps
A8: semanas_semestre | B8: 18 | C8: semanas | D8: Cronograma EPS 2026.2: 10/08 a 14/12.
A9: custo_eps_semana | B9: =B7/B8 | C9: R$/semana | D9: custo_eps / semanas_semestre
A10: Trabalho remoto (energia e internet)
A11: tarifa_kwh | B11: 0.83 | C11: R$/kWh | D11: Tarifa Neoenergia Brasília (planilha de custos 2026.1).
A12: potencia_computador | B12: 40 | C12: W | D12: Consumo médio de notebook (planilha de custos 2026.1: 35 a 40 W).
A13: potencia_modem | B13: 12 | C13: W | D13: Consumo médio de modem (planilha de custos 2026.1: 8 a 12 W).
A14: horas_remotas_semana | B14: 10 | C14: h/semana | D14: Premissa de 2026.1: 10 h remotas por semana. Confirmar com o time.
A15: energia_semana | B15: =(B12+B13)/1000*B11*B14 | C15: R$/semana | D15: (potências em kW) x tarifa x horas remotas
A16: internet_mes | B16: 99.9 | C16: R$/mês | D16: Plano de 600 Mb (planilha de custos 2026.1).
A17: internet_semana | B17: =B16*12/52 | C17: R$/semana | D17: internet_mes x 12 / 52
A18: Equipamento
A19: valor_notebook | B19: 3665.56 | C19: R$ | D19: Notebook de referência Acer Aspire 5, Ryzen 5, 16 GB (planilha de custos 2026.1).
A20: vida_util_meses | B20: 60 | C20: meses | D20: Vida útil de 5 anos (planilha de custos 2026.1).
A21: depreciacao_semana | B21: =B19/(B20*52/12) | C21: R$/semana | D21: valor_notebook / vida útil em semanas
A22: Resultado por integrante
A23: horas_presenciais_semana | B23: 4 | C23: h/semana | D23: Aula de segunda (plano de ensino).
A24: horas_semana_total | B24: =B14+B23 | C24: h/semana | D24: horas remotas + presenciais. Vai para Parametros.horas_semana_pessoa.
A25: custo_membro_semana | B25: =B9+B15+B17+B21 | C25: R$/semana | D25: EPS + energia + internet + depreciação
A26: custo_hora | B26: =B25/B24 | C26: R$/hora | D26: custo_membro_semana / horas_semana_total. Vai para Parametros.custo_hora.
A27: Infraestrutura
A28: infraestrutura_semana | B28: 0 | C28: R$/semana | D28: Deploy no LAPPIS, documentação no GitHub Pages e imagens no Docker Hub: sem custo (planilha de custos 2026.1). Atualizar se houver domínio ou serviço pago.

Sheet Parametros
A1: parametro | B1: valor | C1: unidade | D1: fonte
A2: pessoas | B2: =COUNTA(Integrantes!A2:A1000) | C2: integrantes | D2: Contagem da aba Integrantes
A3: horas_semana_pessoa | B3: =Custos!B24 | C3: horas/semana | D3: Da aba Custos (horas presenciais + remotas)
A4: custo_hora | B4: =ROUND(Custos!B26,2) | C4: R$/hora | D4: Da aba Custos (modelo de custo do aluno, adaptado de 2026.1)
A5: criterio_feito | B5: Done | C5: pipeline do Zenhub | D5: Decisão do time, 27/09/2026
A6: niveis_pontuados | B6: Feature;Task;Bug | C6: tipo de issue | D6: Decisão do time, 27/09/2026: US (Feature no Zenhub) e Task; Bug como Task de correção. US com Tasks filhas não pontua.

Sheet Sprints
A1: sprint | B1: release | C1: inicio | D1: fim | E1: zenhub_sprint_id | F1: observacao | G1: semanas | H1: horas_reais
A2: 1 | B2: R1 | C2: 46258 | D2: 46271 | E2: Z2lkOi8vcmFwdG9yL1NwcmludC81MjU3NTU4 | F2: Quinzenal: diagnóstico e Lean Inception | G2: =IF(C2="","",(D2-C2+1)/7) | H2: =IF(A2="","",SUMIF(Horas!$A:$A,A2,Horas!$C:$C))
A3: 2 | B3: R1 | C3: 46272 | D3: 46285 | E3: Z2lkOi8vcmFwdG9yL1NwcmludC81MjU3NTU5 | F3: Quinzenal: migração dos repositórios e EAP | G3: =IF(C3="","",(D3-C3+1)/7) | H3: =IF(A3="","",SUMIF(Horas!$A:$A,A3,Horas!$C:$C))
A4: 3 | B4: R1 | C4: 46286 | D4: 46292 | E4: Z2lkOi8vcmFwdG9yL1NwcmludC81MjU3NTYw | F4: Semanal a partir daqui | G4: =IF(C4="","",(D4-C4+1)/7) | H4: =IF(A4="","",SUMIF(Horas!$A:$A,A4,Horas!$C:$C))
A5: 4 | B5: R2 | C5: 46293 | D5: 46299 | E5: Z2lkOi8vcmFwdG9yL1NwcmludC81MjU3NTYx | G5: =IF(C5="","",(D5-C5+1)/7) | H5: =IF(A5="","",SUMIF(Horas!$A:$A,A5,Horas!$C:$C))
A6: 5 | B6: R2 | C6: 46300 | D6: 46306 | E6: Z2lkOi8vcmFwdG9yL1NwcmludC81MjU3NTYy | G6: =IF(C6="","",(D6-C6+1)/7) | H6: =IF(A6="","",SUMIF(Horas!$A:$A,A6,Horas!$C:$C))
A7: 6 | B7: R2 | C7: 46307 | D7: 46313 | E7: Z2lkOi8vcmFwdG9yL1NwcmludC81MjU3NTYz | F7: Feriado 12/10 | G7: =IF(C7="","",(D7-C7+1)/7) | H7: =IF(A7="","",SUMIF(Horas!$A:$A,A7,Horas!$C:$C))
A8: 7 | B8: R2 | C8: 46314 | D8: 46320 | E8: Z2lkOi8vcmFwdG9yL1NwcmludC81MjU3NTY0 | G8: =IF(C8="","",(D8-C8+1)/7) | H8: =IF(A8="","",SUMIF(Horas!$A:$A,A8,Horas!$C:$C))
A9: 8 | B9: R3 | C9: 46321 | D9: 46327 | E9: Z2lkOi8vcmFwdG9yL1NwcmludC81MjU3NTY1 | G9: =IF(C9="","",(D9-C9+1)/7) | H9: =IF(A9="","",SUMIF(Horas!$A:$A,A9,Horas!$C:$C))
A10: 9 | B10: R3 | C10: 46328 | D10: 46334 | E10: Z2lkOi8vcmFwdG9yL1NwcmludC81Mjg3ODAw | F10: Feriado 02/11 | G10: =IF(C10="","",(D10-C10+1)/7) | H10: =IF(A10="","",SUMIF(Horas!$A:$A,A10,Horas!$C:$C))
A11: 10 | B11: R3 | C11: 46335 | D11: 46341 | E11: Z2lkOi8vcmFwdG9yL1NwcmludC81MzA5OTI3 | G11: =IF(C11="","",(D11-C11+1)/7) | H11: =IF(A11="","",SUMIF(Horas!$A:$A,A11,Horas!$C:$C))
A12: 11 | B12: R3 | C12: 46342 | D12: 46348 | F12: Sprint ainda não criada no Zenhub | G12: =IF(C12="","",(D12-C12+1)/7) | H12: =IF(A12="","",SUMIF(Horas!$A:$A,A12,Horas!$C:$C))
A13: 12 | B13: R3 | C13: 46349 | D13: 46355 | F13: Sprint ainda não criada no Zenhub | G13: =IF(C13="","",(D13-C13+1)/7) | H13: =IF(A13="","",SUMIF(Horas!$A:$A,A13,Horas!$C:$C))

Sheet Releases
A1: release | B1: entrega | C1: prp_linha_de_base | D1: observacao | E1: sprints | F1: semanas | G1: horas_planejadas | H1: bac_rs | I1: horas_reais
A2: R1 | B2: 46293 | D2: Sem linha de base: o sequenciador da Lean Inception não fechou. O app reconstitui o PRP a partir do Zenhub. | E2: =COUNTIF(Sprints!$B:$B,A2) | F2: =SUMIF(Sprints!$B:$B,A2,Sprints!$G:$G) | G2: =IF(Parametros!$B$3="","",Parametros!$B$2*Parametros!$B$3*F2) | H2: =IF(OR(G2="",Parametros!$B$4=""),"",G2*Parametros!$B$4+F2*Custos!$B$28) | I2: =SUMIF(Sprints!$B:$B,A2,Sprints!$H:$H)
A3: R2 | B3: 46321 | D3: Congelar na planning de 28/09. | E3: =COUNTIF(Sprints!$B:$B,A3) | F3: =SUMIF(Sprints!$B:$B,A3,Sprints!$G:$G) | G3: =IF(Parametros!$B$3="","",Parametros!$B$2*Parametros!$B$3*F3) | H3: =IF(OR(G3="",Parametros!$B$4=""),"",G3*Parametros!$B$4+F3*Custos!$B$28) | I3: =SUMIF(Sprints!$B:$B,A3,Sprints!$H:$H)
A4: R3 | B4: 46356 | D4: Congelar na planning de 26/10. | E4: =COUNTIF(Sprints!$B:$B,A4) | F4: =SUMIF(Sprints!$B:$B,A4,Sprints!$G:$G) | G4: =IF(Parametros!$B$3="","",Parametros!$B$2*Parametros!$B$3*F4) | H4: =IF(OR(G4="",Parametros!$B$4=""),"",G4*Parametros!$B$4+F4*Custos!$B$28) | I4: =SUMIF(Sprints!$B:$B,A4,Sprints!$H:$H)

Sheet Horas
A1: sprint | B1: integrante | C1: horas | D1: observacao
A2: 1 | B2: Alexandre de Sanana Beck
A3: 1 | B3: Antônio José Magalhães Leão Júnior
A4: 1 | B4: Daniel Ferreira Santos Rabelo
A5: 1 | B5: Diego Carlito Rodrigues de Souza
A6: 1 | B6: Diogo Rodrigues Barboza
A7: 1 | B7: Gabriel Marques de Souza
A8: 1 | B8: Gabriel Moura
A9: 1 | B9: Guilherme Storch
A10: 1 | B10: Gustavo Roberto Silva de Melo
A11: 1 | B11: Henrique Camelo Quenino
A12: 1 | B12: Kathlyn Lara Murussi
A13: 1 | B13: Lucas Bottino
... A61: 3 | B61: Wallyson Souza

Sheet Riscos
A1: id | B1: categoria | C1: risco | D1: causa | E1: consequencia | F1: gatilho | G1: probabilidade | H1: impacto | I1: exposicao | J1: nivel | K1: resposta | L1: prevencao | M1: contingencia | N1: responsavel | O1: status | P1: ultima_revisao
A2: R01 | B2: Técnico | C2: Motor de cálculo publicado não corresponde ao código versionado | D2: Core versionado em 1.5.3, PyPI com msgram-core 1.5.4 publicado de código fora do repositório; Service usa 1.4.9 | E2: Nota de qualidade não reproduzível; CLI e Web dão resultados diferentes para o mesmo projeto | F2: Teste de regressão entre CLI e Service com notas diferentes | G2: 4 | H2: 4 | I2: =IF(OR(G2="",H2=""),"",G2*H2) | J2: =IF(I2="","",IF(I2>=15,"Elevado",IF(I2>=6,"Médio","Baixo"))) | K2: Mitigar | L2: TASK05.03 (DOC#50): padronizar msgram-core 1.5.4 no Service e na CLI (PRs Service#19 e CLI#4) | M2: Congelar a versão do Core usada na homologação e documentar a divergência na R1 | N2: Nathan Benigno Ponce de Abreu | O2: Aberto | P2: 46292
A3: R02 | B3: Técnico | C3: Endpoint público expõe e-mail de todos os usuários | D3: GET /users/ do Service sem autenticação (diagnóstico, gravidade Crítico) | E3: Vazamento de dado pessoal (LGPD) no ambiente publicado | F3: Endpoint respondendo sem token em homologação | G3: 4 | H3: 5 | I3: =IF(OR(G3="",H3=""),"",G3*H3) | J3: =IF(I3="","",IF(I3>=15,"Elevado",IF(I3>=6,"Médio","Baixo"))) | K3: Mitigar | L3: BUG05.01 (DOC#52): corrigir falhas de segurança MSG-03, MSG-12 e MSG-13; Django já atualizado para 5.2 LTS (Service#3) | M3: Desativar a rota em homologação até a correção | N3: Marcos Antonio Teles de Castilhos | O3: Aberto | P3: 46292
A4: R03 | B4: Técnico | C4: Nenhum portão de qualidade bloqueante nos repositórios | D4: CI não é exigida antes do merge e o Service não define fail_under de cobertura | E4: Regressões e queda de cobertura entram na develop sem aviso | F4: PR mergeado com CI falhando ou sem rodar | G4: 4 | H4: 3 | I4: =IF(OR(G4="",H4=""),"",G4*H4) | J4: =IF(I4="","",IF(I4>=15,"Elevado",IF(I4>=6,"Médio","Baixo"))) | K4: Mitigar | L4: DOC#74: governança de branches, portões de CI e gestão de secrets nos repositórios centrais | M4: Revisão manual obrigatória da CI no template de PR | N4: Luciano Freitas | O4: Aberto | P4: 46292
A5: R04 | B5: Organizacional | C5: Coordenação técnica entre squads que atravessam repositórios | D5: Fatias verticais tocam vários repositórios (ex.: dívida técnica em Action, Parser, CLI e Front) | E5: Tasks bloqueadas esperando outro repositório; retrabalho de integração | F5: Issue bloqueada por outra de outro repositório por mais de uma sprint | G5: 3 | H5: 3 | I5: =IF(OR(G5="",H5=""),"",G5*H5) | J5: =IF(I5="","",IF(I5>=15,"Elevado",IF(I5>=6,"Médio","Baixo"))) | K5: Mitigar | L5: Modelo de squads por release (docs/planejamento/squads) e dependências registradas no Zenhub (blocking) | M5: Sessão de integração na planning de segunda | N5: Milena Fernandes Rocha | O5: Aberto | P5: 46292
A6: R05 | B6: Gerencial | C6: Objetivo do semestre ainda não fechado com o PO | D6: Primeira reunião com o PO foi expositiva; Visão do Produto ainda em andamento (DOC#18) | E6: Backlog priorizado sem validação; risco de entregar o que o PO não espera | F6: US voltando de 'Aguardando validação do PO (DoR)' | G6: 3 | H6: 4 | I6: =IF(OR(G6="",H6=""),"",G6*H6) | J6: =IF(I6="","",IF(I6>=15,"Elevado",IF(I6>=6,"Médio","Baixo"))) | K6: Mitigar | L6: Pauta preparada para a reunião semanal com o PO; validar Visão do Produto e Canvas MVP | M6: Escalar ao professor se não houver validação até a R2 | N6: Guilherme Storch | O6: Aberto | P6: 46292
A7: R06 | B7: Organizacional | C7: Desbalanceamento de contribuições num time de 20 pessoas | D7: Time grande com níveis de conhecimento diferentes (aba Habilidades); várias issues sem responsável | E7: Concentração de carga e avaliação individual prejudicada na R2 (contribuições equilibradas) | F7: Integrante sem horas ou sem issue atribuída na sprint | G7: 3 | H7: 3 | I7: =IF(OR(G7="",H7=""),"",G7*H7) | J7: =IF(I7="","",IF(I7>=15,"Elevado",IF(I7>=6,"Médio","Baixo"))) | K7: Aceitar | L7: Acompanhar horas por integrante (aba Horas) e issues por pessoa no dashboard | M7: Redistribuir tasks na planning seguinte | N7: Milena Fernandes Rocha | O7: Em monitoramento | P7: 46292
A8: R07 | B8: Técnico | C8: Métricas de repositórios publicadas em repos de semestres anteriores | D8: metrics.yml de alguns repositórios ainda publica no repositório central (MeasureSoftGram-Core aparece junto do 2026.2-Core) | E8: Dashboard com dado misturado ou faltando | F8: Arquivo de métricas com prefixo sem '2026.2-' em Analytics/data | G8: 4 | H8: 3 | I8: =IF(OR(G8="",H8=""),"",G8*H8) | J8: =IF(I8="","",IF(I8>=15,"Elevado",IF(I8>=6,"Médio","Baixo"))) | K8: Mitigar | L8: DOC#14 (organização dos repositórios): apontar o metrics.yml de todos para o docs-eps de 2026.2 | M8: Filtrar no dashboard só repositórios 2026.2 | N8: Milena Fernandes Rocha | O8: Aberto | P8: 46292
A9: R08 | B9: Técnico | C9: Cobertura abaixo da meta de 85% em Front (80,4%), Service (82,4%) e Action (82,7%) | D9: Suítes herdadas sem manutenção desde 2024 e sem portão de cobertura | E9: Critério da R1 (cobertura ≥ 85%) não atendido em 3 de 7 repositórios | F9: Cobertura abaixo de 85% na última coleta do SonarCloud | G9: 4 | H9: 3 | I9: =IF(OR(G9="",H9=""),"",G9*H9) | J9: =IF(I9="","",IF(I9>=15,"Elevado",IF(I9>=6,"Médio","Baixo"))) | K9: Mitigar | L9: TASK03.02 (DOC#57): saneamento do backlog técnico; testes nos componentes com menor cobertura (painel do dashboard) | M9: Priorizar testes do Front e do Service na sprint 4 | N9: Antônio José Magalhães Leão Júnior | O9: Aberto | P9: 46292
A10: R09 | B10: Técnico | C10: Taxa de falha da CI em 35% (65 de 188 execuções), com Service em 45% e Action em 41% | D10: Workflows antigos (actions descontinuadas) e metrics.yml falhando no Front e no Service | E10: Time aprende a ignorar a CI; métricas deixam de ser coletadas | F10: Taxa de falha acima de 20% no dashboard | G10: 4 | H10: 3 | I10: =IF(OR(G10="",H10=""),"",G10*H10) | J10: =IF(I10="","",IF(I10>=15,"Elevado",IF(I10>=6,"Médio","Baixo"))) | K10: Mitigar | L10: TASK03.01 (DOC#73) e DOC#74: atualizar workflows e corrigir o metrics.yml | M10: Rodar o metrics.yml manualmente (workflow_dispatch) antes de cada release | N10: Luciano Freitas | O10: Aberto | P10: 46292
A11: R10 | B11: Gerencial | C11: Sequenciador da Lean Inception atrasado frente ao cronograma | D11: Sequenciador previsto para 24/08 não fechou | E11: R1 sem linha de base de escopo (PRP); fatias verticais não decompostas na EAP | F11: Planning da release sem US priorizadas | G11: 5 | H11: 4 | I11: =IF(OR(G11="",H11=""),"",G11*H11) | J11: =IF(I11="","",IF(I11>=15,"Elevado",IF(I11>=6,"Médio","Baixo"))) | K11: Mitigar | L11: EAP com pacotes de planejamento; linha de base da R2 congelada na planning de 28/09 | M11: Usar o PRP reconstituído do Zenhub na R1 e declarar no dashboard | N11: Guilherme Storch | O11: Materializado | P11: 46292
A12: R11 | B12: Técnico | C12: AI e Plugin sem projeto válido no SonarCloud | D12: A coleta do metrics.yml grava erro de component key para AI e Plugin | E12: Qualidade de 2 dos 9 módulos fica invisível no dashboard e na avaliação | F12: Arquivo de coleta com 'Component key' em vez de métricas | G12: 5 | H12: 3 | I12: =IF(OR(G12="",H12=""),"",G12*H12) | J12: =IF(I12="","",IF(I12>=15,"Elevado",IF(I12>=6,"Médio","Baixo"))) | K12: Mitigar | L12: Criar os projetos no SonarCloud da organização e corrigir a chave no metrics.yml | M12: Declarar no dashboard os módulos sem métrica | N12: Antônio José Magalhães Leão Júnior | O12: Aberto | P12: 46292
A13: R12 | B13: Técnico | C13: Rating de segurança E no Plugin e C no Service (SonarCloud) | D13: Vulnerabilidades apontadas pelo SonarCloud na última coleta (security_rating 5 no Plugin, 3 no Service) | E13: Produto publicado com vulnerabilidade conhecida | F13: security_rating acima de 1 (A) em qualquer repositório | G13: 4 | H13: 4 | I13: =IF(OR(G13="",H13=""),"",G13*H13) | J13: =IF(I13="","",IF(I13>=15,"Elevado",IF(I13>=6,"Médio","Baixo"))) | K13: Mitigar | L13: Revisar os security hotspots do Plugin e do Service e corrigir as vulnerabilidades | M13: Não publicar nova versão do Plugin até o rating voltar para A | N13: Nathan Benigno Ponce de Abreu | O13: Aberto | P13: 46292
... A15: R14 | B15: Gerencial | C15: Horas reais não registradas pela equipe | D15: Registro de horas criado só em 27/09; sprints 1 a 3 sem dado | E15: Sem custo real (AC) não há CPI nem EAC; exigência da disciplina não atendida | F15: Integrantes sem horas na aba Horas após a planning | G15: 4 | H15: 3 | I15: =IF(OR(G15="",H15=""),"",G15*H15) | J15: =IF(I15="","",IF(I15>=15,"Elevado",IF(I15>=6,"Médio","Baixo"))) | K15: Mitigar | L15: Lançar horas toda segunda na planning (decisão D3) | M15: Declarar o período sem dado no dashboard; não estimar retroativamente | N15: Daniel Ferreira Santos Rabelo | O15: Aberto | P15: 46292
I16: =IF(OR(G16="",H16=""),"",G16*H16) | J16: =IF(I16="","",IF(I16>=15,"Elevado",IF(I16>=6,"Médio","Baixo")))
I17: =IF(OR(G17="",H17=""),"",G17*H17) | J17: =IF(I17="","",IF(I17>=15,"Elevado",IF(I17>=6,"Médio","Baixo")))
I18: =IF(OR(G18="",H18=""),"",G18*H18) | J18: =IF(I18="","",IF(I18>=15,"Elevado",IF(I18>=6,"Médio","Baixo")))
I19: =IF(OR(G19="",H19=""),"",G19*H19) | J19: =IF(I19="","",IF(I19>=15,"Elevado",IF(I19>=6,"Médio","Baixo")))
I20: =IF(OR(G20="",H20=""),"",G20*H20) | J20: =IF(I20="","",IF(I20>=15,"Elevado",IF(I20>=6,"Médio","Baixo")))
I21: =IF(OR(G21="",H21=""),"",G21*H21) | J21: =IF(I21="","",IF(I21>=15,"Elevado",IF(I21>=6,"Médio","Baixo")))
I22: =IF(OR(G22="",H22=""),"",G22*H22) | J22: =IF(I22="","",IF(I22>=15,"Elevado",IF(I22>=6,"Médio","Baixo")))
I23: =IF(OR(G23="",H23=""),"",G23*H23) | J23: =IF(I23="","",IF(I23>=15,"Elevado",IF(I23>=6,"Médio","Baixo")))
I24: =IF(OR(G24="",H24=""),"",G24*H24) | J24: =IF(I24="","",IF(I24>=15,"Elevado",IF(I24>=6,"Médio","Baixo")))
I25: =IF(OR(G25="",H25=""),"",G25*H25) | J25: =IF(I25="","",IF(I25>=15,"Elevado",IF(I25>=6,"Médio","Baixo")))
I26: =IF(OR(G26="",H26=""),"",G26*H26) | J26: =IF(I26="","",IF(I26>=15,"Elevado",IF(I26>=6,"Médio","Baixo")))
I27: =IF(OR(G27="",H27=""),"",G27*H27) | J27: =IF(I27="","",IF(I27>=15,"Elevado",IF(I27>=6,"Médio","Baixo")))
... I40: =IF(OR(G40="",H40=""),"",G40*H40) | J40: =IF(I40="","",IF(I40>=15,"Elevado",IF(I40>=6,"Médio","Baixo")))

Sheet Decisoes
A1: data | B1: sprint | C1: tipo | D1: metrica | E1: causa | F1: decisao | G1: evidencia | H1: criterio_sucesso | I1: resultado | J1: status
A2: 46292 | B2: 3 | C2: Gerencial | D2: Calendário de sprints | E2: Três calendários em uso (planilha antiga quinzenal com R1 até 04/10, Zenhub e página de Planejamento). Só o do Zenhub fecha nas datas das releases. | F2: Adotar o calendário do Zenhub como linha de base: R1 com 3 sprints, R2 com 4 e R3 com 5. | G2: Aba Sprints; Analytics/planilhas/sprints.csv; docs/planejamento/decisoes.mdx (D1) | H2: Todas as sprints até 29/11 criadas no Zenhub com as mesmas datas da planilha | J2: Vigente
A3: 46292 | B3: 3 | C3: Gerencial | D3: Velocity / pontos em Done | E3: Snapshot do Zenhub de 27/09: 0 pontos em Done na R1, issues fechadas fora do pipeline Done e US/Tasks sem estimativa; pontos em Sub-tasks. | F3: Feito = pipeline Done. Story points só em US e Task (US decomposta não pontua; Épicos e Sub-tasks não pontuam). | G3: Aba Parametros (criterio_feito, niveis_pontuados); Analytics/src/gestao.py; docs/planejamento/decisoes.mdx (D2) | H3: Zero pendências no painel de confiabilidade do Zenhub na planning de 28/09 | J3: Vigente
A4: 46292 | B4: 3 | C4: Gerencial | D4: Custo (BAC e AC) | E4: EVM sem orçamento nem custo real: não havia custo/hora definido nem registro de horas; a disciplina exige horas reais. | F4: Usar o modelo de custo do aluno de 2026.1 atualizado (R$ 23,53/h) e registrar horas de cada integrante toda segunda a partir de 28/09. | G4: Abas Custos, Parametros e Horas; docs/planejamento/custos.mdx; docs/planejamento/decisoes.mdx (D3) | H4: 20 de 20 integrantes com horas na sprint 4 e CPI calculado no dashboard | J4: Planejada

Sheet Integrantes
A1: nome | B1: github | C1: horas_registradas
A2: Alexandre de Sanana Beck | B2: zzzBECK | C2: =SUMIF(Horas!$B:$B,$A2,Horas!$C:$C)
A3: Antônio José Magalhães Leão Júnior | B3: antonioleaojr | C3: =SUMIF(Horas!$B:$B,$A3,Horas!$C:$C)
A4: Daniel Ferreira Santos Rabelo | B4: DanielFsR | C4: =SUMIF(Horas!$B:$B,$A4,Horas!$C:$C)
A5: Diego Carlito Rodrigues de Souza | B5: DiegoCarlito | C5: =SUMIF(Horas!$B:$B,$A5,Horas!$C:$C)
A6: Diogo Rodrigues Barboza | B6: Diogo-Barboza | C6: =SUMIF(Horas!$B:$B,$A6,Horas!$C:$C)
A7: Gabriel Marques de Souza | B7: GabrielMS00 | C7: =SUMIF(Horas!$B:$B,$A7,Horas!$C:$C)
A8: Gabriel Moura | B8: thegm445 | C8: =SUMIF(Horas!$B:$B,$A8,Horas!$C:$C)
A9: Guilherme Storch | B9: storch7 | C9: =SUMIF(Horas!$B:$B,$A9,Horas!$C:$C)
A10: Gustavo Roberto Silva de Melo | B10: gusrberto | C10: =SUMIF(Horas!$B:$B,$A10,Horas!$C:$C)
A11: Henrique Camelo Quenino | B11: henriquecq | C11: =SUMIF(Horas!$B:$B,$A11,Horas!$C:$C)
A12: Kathlyn Lara Murussi | B12: klmurussi | C12: =SUMIF(Horas!$B:$B,$A12,Horas!$C:$C)
A13: Lucas Bottino | B13: bottinolucas | C13: =SUMIF(Horas!$B:$B,$A13,Horas!$C:$C)
... A21: Wallyson Souza | B21: devwallyson | C21: =SUMIF(Horas!$B:$B,$A21,Horas!$C:$C)

Sheet Listas
A1: escala | B1: probabilidade | C1: impacto | D1: resposta | E1: status | F1: categoria_EAR | G1: tipo_decisao | H1: pipeline_feito
A2: 1 | B2: Muito baixa (0-19%) | C2: Muito baixo | D2: Evitar | E2: Aberto | F2: Técnico | G2: Técnica | H2: Done
A3: 2 | B3: Baixa (20-39%) | C3: Baixo | D3: Mitigar | E3: Em monitoramento | F3: Gerencial | G3: Gerencial
A4: 3 | B4: Média (40-59%) | C4: Médio | D4: Transferir | E4: Materializado | F4: Organizacional
A5: 4 | B5: Alta (60-79%) | C5: Alto | D5: Aceitar | E5: Encerrado | F5: Externo
A6: 5 | B6: Muito alta (80-100%) | C6: Muito alto | D6: Escalar
