Workbook

Sheet Leia-me
A1: MeasureSoftGram 2026.2 · Custos e AgileEVM
A2: Mesma estrutura da planilha de 2026.1 (Custos, Planejamento, Sumário EVM, Valor Agregado, Velocity, Índices e Burndown). Toda coluna tem uma nota no cabeçalho dizendo de onde vem o dado e como é calculado (passe o mouse no título).
A4: Cores
A5: Amarelo | B5: Premissa ou dado de entrada: é o que o time preenche.
A6: Azul-claro | B6: Calculado por fórmula. Não digitar por cima.
A8: Abas
A9: Custos | B9: Premissas de custo (UnB, energia, internet, notebook, infraestrutura) → custo de um integrante por semana e custo/hora.
A10: Planejamento | B10: Quem está no time em cada semana (1/0) → custo planejado de cada semana. É daqui que sai o orçamento (BAC).
A11: Horas | B11: Opcional. Horas reais por pessoa e sprint. Com horas, o AC usa horas × custo/hora; sem horas, usa o custo planejado.
A12: Sumário EVM | B12: Uma linha por release: linha de base (PRP), orçamento (BAC) e a situação na última sprint preenchida (SPI, CPI, término estimado).
A13: EVM - Valor Agregado | B13: Uma linha por sprint com o AgileEVM completo. O time preenche só PP, PC e PA (amarelo) ao fim de cada sprint, a partir do Zenhub.
A14: EVM - Velocity | B14: Velocity por sprint e média; gráfico de planejado × concluído.
A15: EVM - Índices e Burndown | B15: SPI, CPI e burndown por sprint, com gráficos.
A17: Rotina
A18: Fim de cada sprint | B18: 1) Copiar PP, PC e PA do Zenhub para a aba EVM - Valor Agregado (o dashboard mostra os números prontos). 2) Se alguém saiu/entrou, ajustar a aba Planejamento. 3) (Opcional) lançar as horas.
A19: Abertura de release | B19: Congelar o PRP linha de base na aba Sumário EVM (R2 na planning de 28/09; R3 na de 26/10).
A21: Dashboard
A22: Publicar | B22: Arquivo → Compartilhar → Publicar na Web → escolher a aba → CSV. Publicar: Custos, Planejamento, Horas, Sumário EVM, EVM - Valor Agregado e EVM - Velocity, e colar os links em Analytics/config.py.

Sheet Custos
A1: chave | B1: grupo | C1: item | D1: valor | E1: unidade | F1: fonte | G1: cálculo
A2: custo_anual_aluno | B2: Disciplina (UnB) | C2: Custo anual de um aluno de universidade federal | D2: 52533 | E2: R$/ano | F2: Valor de referência da planilha de custos do MeasureSoftGram 2026.1 (custo médio anual por aluno de universidade federal). | G2: premissa
A3: creditos_ano | B3: Disciplina (UnB) | C3: Créditos cursados por ano | D3: 40 | E3: créditos | F3: Planilha de custos 2026.1. | G3: premissa
A4: custo_credito | B4: Disciplina (UnB) | C4: Custo de um crédito | D4: =D2/D3 | E4: R$ | G4: custo_anual_aluno ÷ creditos_ano
A5: creditos_eps | B5: Disciplina (UnB) | C5: Créditos de EPS | D5: 4 | E5: créditos | F5: Plano de ensino EPS 2026.2: 60 h, 4 créditos. | G5: premissa
A6: custo_eps | B6: Disciplina (UnB) | C6: Custo de cursar EPS no semestre | D6: =D4*D5 | E6: R$ | G6: custo_credito × creditos_eps
A7: semanas_semestre | B7: Disciplina (UnB) | C7: Semanas do semestre | D7: 18 | E7: semanas | F7: Cronograma EPS 2026.2 (10/08 a 14/12). | G7: premissa
A8: custo_eps_semana | B8: Disciplina (UnB) | C8: Custo de EPS por semana | D8: =D6/D7 | E8: R$/semana | G8: custo_eps ÷ semanas_semestre
A9: horas_remotas_semana | B9: Trabalho remoto | C9: Horas de trabalho remoto por semana | D9: 10 | E9: h/semana | F9: Premissa de 2026.1 (10 h remotas). Confirmar com o time. | G9: premissa
A10: tarifa_kwh | B10: Trabalho remoto | C10: Tarifa de energia | D10: 0.83 | E10: R$/kWh | F10: Neoenergia Brasília (planilha de custos 2026.1). | G10: premissa
A11: potencia_computador | B11: Trabalho remoto | C11: Consumo do computador | D11: 40 | E11: W | F11: Notebook: 35 a 40 W (planilha de custos 2026.1). | G11: premissa
A12: potencia_modem | B12: Trabalho remoto | C12: Consumo do modem | D12: 12 | E12: W | F12: Modem: 8 a 12 W (planilha de custos 2026.1). | G12: premissa
A13: energia_semana | B13: Trabalho remoto | C13: Energia por semana | D13: =(D11+D12)/1000*D10*D9 | E13: R$/semana | G13: (W computador + W modem) ÷ 1000 × tarifa × horas remotas
A14: internet_mes | B14: Trabalho remoto | C14: Internet por mês | D14: 99.9 | E14: R$/mês | F14: Plano Claro 600 Mb (planilha de custos 2026.1). | G14: premissa
A15: internet_semana | B15: Trabalho remoto | C15: Internet por semana | D15: =D14*12/52 | E15: R$/semana | G15: internet_mes × 12 ÷ 52
A16: valor_notebook | B16: Equipamento | C16: Notebook de referência | D16: 3665.56 | E16: R$ | F16: Acer Aspire 5, Ryzen 5, 16 GB (planilha de custos 2026.1). | G16: premissa
A17: vida_util_meses | B17: Equipamento | C17: Vida útil | D17: 60 | E17: meses | F17: 5 anos (planilha de custos 2026.1). | G17: premissa
A18: depreciacao_semana | B18: Equipamento | C18: Depreciação por semana | D18: =D16/(D17*52/12) | E18: R$/semana | G18: valor_notebook ÷ vida útil em semanas
A19: deploy_semana | B19: Infraestrutura | C19: Deploy (servidor) | D19: 0 | E19: R$/semana | F19: Deploy no LAPPIS, sem custo (planilha de custos 2026.1). Atualizar se contratar serviço. | G19: premissa
A20: dominio_ano | B20: Infraestrutura | C20: Domínio | D20: 0 | E20: R$/ano | F20: Sem domínio próprio em 2026.2 (docs no GitHub Pages). Em 2026.1: R$ 49,99/ano. | G20: premissa
A21: infra_semana | B21: Infraestrutura | C21: Infraestrutura por semana | D21: =D19+D20/52 | E21: R$/semana | G21: deploy_semana + dominio_ano ÷ 52
A22: horas_presenciais_semana | B22: Resultado | C22: Horas presenciais por semana | D22: 4 | E22: h/semana | F22: Aula de segunda (plano de ensino). | G22: premissa
A23: horas_semana_total | B23: Resultado | C23: Horas por integrante por semana | D23: =D9+D22 | E23: h/semana | G23: horas remotas + presenciais
A24: custo_membro_semana | B24: Resultado | C24: Custo de um integrante por semana | D24: =D8+D13+D15+D18 | E24: R$/semana | G24: EPS + energia + internet + depreciação
A25: custo_hora | B25: Resultado | C25: Custo por hora de trabalho | D25: =D24/D23 | E25: R$/h | G25: custo_membro_semana ÷ horas por semana. Converte horas reais (aba Horas) em R$.
A26: integrantes | B26: Resultado | C26: Integrantes no time | D26: =COUNTA(Planejamento!A2:A31) | E26: pessoas | F26: Aba Planejamento. | G26: contagem de nomes na aba Planejamento
A27: bac_total | B27: Resultado | C27: Orçamento total do projeto (BAC) | D27: =SUM(Planejamento!B33:O33) | E27: R$ | F27: Aba Planejamento. | G27: soma do custo planejado de todas as semanas

Sheet Planejamento
A1: Integrante | B1: 46258 | C1: 46265 | D1: 46272 | E1: 46279 | F1: 46286 | G1: 46293 | H1: 46300 | I1: 46307 | J1: 46314 | K1: 46321 | L1: 46328 | M1: 46335 | N1: 46342 | O1: 46349 | P1: Semanas ativas
A2: Alexandre de Sanana Beck | B2: 1 | C2: 1 | D2: 1 | E2: 1 | F2: 1 | G2: 1 | H2: 1 | I2: 1 | J2: 1 | K2: 1 | L2: 1 | M2: 1 | N2: 1 | O2: 1 | P2: =SUM(B2:O2)
A3: Antônio José Magalhães Leão Júnior | B3: 1 | C3: 1 | D3: 1 | E3: 1 | F3: 1 | G3: 1 | H3: 1 | I3: 1 | J3: 1 | K3: 1 | L3: 1 | M3: 1 | N3: 1 | O3: 1 | P3: =SUM(B3:O3)
A4: Daniel Ferreira Santos Rabelo | B4: 1 | C4: 1 | D4: 1 | E4: 1 | F4: 1 | G4: 1 | H4: 1 | I4: 1 | J4: 1 | K4: 1 | L4: 1 | M4: 1 | N4: 1 | O4: 1 | P4: =SUM(B4:O4)
A5: Diego Carlito Rodrigues de Souza | B5: 1 | C5: 1 | D5: 1 | E5: 1 | F5: 1 | G5: 1 | H5: 1 | I5: 1 | J5: 1 | K5: 1 | L5: 1 | M5: 1 | N5: 1 | O5: 1 | P5: =SUM(B5:O5)
A6: Diogo Rodrigues Barboza | B6: 1 | C6: 1 | D6: 1 | E6: 1 | F6: 1 | G6: 1 | H6: 1 | I6: 1 | J6: 1 | K6: 1 | L6: 1 | M6: 1 | N6: 1 | O6: 1 | P6: =SUM(B6:O6)
A7: Gabriel Marques de Souza | B7: 1 | C7: 1 | D7: 1 | E7: 1 | F7: 1 | G7: 1 | H7: 1 | I7: 1 | J7: 1 | K7: 1 | L7: 1 | M7: 1 | N7: 1 | O7: 1 | P7: =SUM(B7:O7)
A8: Gabriel Moura | B8: 1 | C8: 1 | D8: 1 | E8: 1 | F8: 1 | G8: 1 | H8: 1 | I8: 1 | J8: 1 | K8: 1 | L8: 1 | M8: 1 | N8: 1 | O8: 1 | P8: =SUM(B8:O8)
A9: Guilherme Storch | B9: 1 | C9: 1 | D9: 1 | E9: 1 | F9: 1 | G9: 1 | H9: 1 | I9: 1 | J9: 1 | K9: 1 | L9: 1 | M9: 1 | N9: 1 | O9: 1 | P9: =SUM(B9:O9)
A10: Gustavo Roberto Silva de Melo | B10: 1 | C10: 1 | D10: 1 | E10: 1 | F10: 1 | G10: 1 | H10: 1 | I10: 1 | J10: 1 | K10: 1 | L10: 1 | M10: 1 | N10: 1 | O10: 1 | P10: =SUM(B10:O10)
A11: Henrique Camelo Quenino | B11: 1 | C11: 1 | D11: 1 | E11: 1 | F11: 1 | G11: 1 | H11: 1 | I11: 1 | J11: 1 | K11: 1 | L11: 1 | M11: 1 | N11: 1 | O11: 1 | P11: =SUM(B11:O11)
A12: Kathlyn Lara Murussi | B12: 1 | C12: 1 | D12: 1 | E12: 1 | F12: 1 | G12: 1 | H12: 1 | I12: 1 | J12: 1 | K12: 1 | L12: 1 | M12: 1 | N12: 1 | O12: 1 | P12: =SUM(B12:O12)
A13: Lucas Bottino | B13: 1 | C13: 1 | D13: 1 | E13: 1 | F13: 1 | G13: 1 | H13: 1 | I13: 1 | J13: 1 | K13: 1 | L13: 1 | M13: 1 | N13: 1 | O13: 1 | P13: =SUM(B13:O13)
... A21: Wallyson Souza | B21: 1 | C21: 1 | D21: 1 | E21: 1 | F21: 1 | G21: 1 | H21: 1 | I21: 1 | J21: 1 | K21: 1 | L21: 1 | M21: 1 | N21: 1 | O21: 1 | P21: =SUM(B21:O21)
A32: Integrantes ativos | B32: =SUM(B2:B31) | C32: =SUM(C2:C31) | D32: =SUM(D2:D31) | E32: =SUM(E2:E31) | F32: =SUM(F2:F31) | G32: =SUM(G2:G31) | H32: =SUM(H2:H31) | I32: =SUM(I2:I31) | ... O32: =SUM(O2:O31)
A33: Custo planejado da semana (R$) | B33: =B32*Custos!$D$24+Custos!$D$21 | C33: =C32*Custos!$D$24+Custos!$D$21 | D33: =D32*Custos!$D$24+Custos!$D$21 | E33: =E32*Custos!$D$24+Custos!$D$21 | F33: =F32*Custos!$D$24+Custos!$D$21 | G33: =G32*Custos!$D$24+Custos!$D$21 | H33: =H32*Custos!$D$24+Custos!$D$21 | I33: =I32*Custos!$D$24+Custos!$D$21 | ... O33: =O32*Custos!$D$24+Custos!$D$21
A34: Release | B34: R1 | C34: R1 | D34: R1 | E34: R1 | F34: R1 | G34: R2 | H34: R2 | I34: R2 | J34: R2 | K34: R3 | L34: R3 | M34: R3 | N34: R3 | O34: R3
A35: Sprint | B35: 1 | C35: 1 | D35: 2 | E35: 2 | F35: 3 | G35: 4 | H35: 5 | I35: 6 | J35: 7 | K35: 8 | L35: 9 | M35: 10 | N35: 11 | O35: 12

Sheet Horas
A1: Sprint | B1: Integrante | C1: Horas | D1: Observação
A2: 1 | B2: Alexandre de Sanana Beck
A3: 1 | B3: Antônio José Magalhães Leão Júnior
A4: 1 | B4: Daniel Ferreira Santos Rabelo
A5: 1 | B5: Diego Carlito Rodrigues de Souza
A6: 1 | B6: Diogo Rodrigues Barboza
A7: 1 | B7: Gabriel Marques de Souza
A8: 1 | B8: Gabriel Moura
A9: 1 | B9: Guilherme Storch
A10: 1 | B10: Gustavo Roberto Silva de Melo
A11: 1 | B11: Henrique Camelo Quenino
A12: 1 | B12: Kathlyn Lara Murussi
A13: 1 | B13: Lucas Bottino
... A81: 4 | B81: Wallyson Souza

Sheet Sumário EVM
A1: Release | B1: Entrega | C1: Início | D1: Fim | E1: Sprints (L) | F1: Semanas | G1: PRP linha de base | H1: PRP atual | I1: Pontos concluídos (RPC) | J1: Orçamento (BAC) | K1: PV | L1: EV | M1: AC | N1: SPI | O1: CPI | P1: Término estimado (RD) | Q1: Observação
A2: R1 | B2: 46293 | C2: =_xlfn.MINIFS('EVM - Valor Agregado'!$C$2:$C$13,'EVM - Valor Agregado'!$A$2:$A$13,$A2) | D2: =_xlfn.MAXIFS('EVM - Valor Agregado'!$D$2:$D$13,'EVM - Valor Agregado'!$A$2:$A$13,$A2) | E2: =COUNTIF('EVM - Valor Agregado'!$A$2:$A$13,$A2) | F2: =SUMIFS('EVM - Valor Agregado'!$E$2:$E$13,'EVM - Valor Agregado'!$A$2:$A$13,$A2) | G2: 6 | H2: =IF(_xlfn.MAXIFS('EVM - Valor Agregado'!$B$2:$B$13,'EVM - Valor Agregado'!$A$2:$A$13,$A2,'EVM - Valor Agregado'!$G$2:$G$13,"<>")=0,"",SUMIFS('EVM - Valor Agregado'!$J$2:$J$13,'EVM - Valor Agregado'!$A$2:$A$13,$A2,'EVM - Valor Agregado'!$B$2:$B$13,_xlfn.MAXIFS('EVM - Valor Agregado'!$B$2:$B$13,'EVM - Valor Agregado'!$A$2:$A$13,$A2,'EVM - Valor Agregado'!$G$2:$G$13,"<>"))) | I2: =IF(_xlfn.MAXIFS('EVM - Valor Agregado'!$B$2:$B$13,'EVM - Valor Agregado'!$A$2:$A$13,$A2,'EVM - Valor Agregado'!$G$2:$G$13,"<>")=0,"",SUMIFS('EVM - Valor Agregado'!$K$2:$K$13,'EVM - Valor Agregado'!$A$2:$A$13,$A2,'EVM - Valor Agregado'!$B$2:$B$13,_xlfn.MAXIFS('EVM - Valor Agregado'!$B$2:$B$13,'EVM - Valor Agregado'!$A$2:$A$13,$A2,'EVM - Valor Agregado'!$G$2:$G$13,"<>"))) | J2: =SUMPRODUCT((Planejamento!$B$1:$O$1>=C2)*(Planejamento!$B$1:$O$1<=D2)*Planejamento!$B$33:$O$33) | K2: =IF(_xlfn.MAXIFS('EVM - Valor Agregado'!$B$2:$B$13,'EVM - Valor Agregado'!$A$2:$A$13,$A2,'EVM - Valor Agregado'!$G$2:$G$13,"<>")=0,"",SUMIFS('EVM - Valor Agregado'!$P$2:$P$13,'EVM - Valor Agregado'!$A$2:$A$13,$A2,'EVM - Valor Agregado'!$B$2:$B$13,_xlfn.MAXIFS('EVM - Valor Agregado'!$B$2:$B$13,'EVM - Valor Agregado'!$A$2:$A$13,$A2,'EVM - Valor Agregado'!$G$2:$G$13,"<>"))) | L2: =IF(_xlfn.MAXIFS('EVM - Valor Agregado'!$B$2:$B$13,'EVM - Valor Agregado'!$A$2:$A$13,$A2,'EVM - Valor Agregado'!$G$2:$G$13,"<>")=0,"",SUMIFS('EVM - Valor Agregado'!$U$2:$U$13,'EVM - Valor Agregado'!$A$2:$A$13,$A2,'EVM - Valor Agregado'!$B$2:$B$13,_xlfn.MAXIFS('EVM - Valor Agregado'!$B$2:$B$13,'EVM - Valor Agregado'!$A$2:$A$13,$A2,'EVM - Valor Agregado'!$G$2:$G$13,"<>"))) | M2: =IF(_xlfn.MAXIFS('EVM - Valor Agregado'!$B$2:$B$13,'EVM - Valor Agregado'!$A$2:$A$13,$A2,'EVM - Valor Agregado'!$G$2:$G$13,"<>")=0,"",SUMIFS('EVM - Valor Agregado'!$S$2:$S$13,'EVM - Valor Agregado'!$A$2:$A$13,$A2,'EVM - Valor Agregado'!$B$2:$B$13,_xlfn.MAXIFS('EVM - Valor Agregado'!$B$2:$B$13,'EVM - Valor Agregado'!$A$2:$A$13,$A2,'EVM - Valor Agregado'!$G$2:$G$13,"<>"))) | N2: =IF(OR(K2="",K2=0),"",L2/K2) | O2: =IF(OR(M2="",M2=0),"",L2/M2) | P2: =IF(OR(N2="",N2=0),"",C2+(D2-C2+1)/N2) | Q2: Linha de base reconstituída: pontos da sprint 1 no Zenhub. Escopo foi entrando nas sprints 2 e 3 (PA).
A3: R2 | B3: 46321 | C3: =_xlfn.MINIFS('EVM - Valor Agregado'!$C$2:$C$13,'EVM - Valor Agregado'!$A$2:$A$13,$A3) | D3: =_xlfn.MAXIFS('EVM - Valor Agregado'!$D$2:$D$13,'EVM - Valor Agregado'!$A$2:$A$13,$A3) | E3: =COUNTIF('EVM - Valor Agregado'!$A$2:$A$13,$A3) | F3: =SUMIFS('EVM - Valor Agregado'!$E$2:$E$13,'EVM - Valor Agregado'!$A$2:$A$13,$A3) | H3: =IF(_xlfn.MAXIFS('EVM - Valor Agregado'!$B$2:$B$13,'EVM - Valor Agregado'!$A$2:$A$13,$A3,'EVM - Valor Agregado'!$G$2:$G$13,"<>")=0,"",SUMIFS('EVM - Valor Agregado'!$J$2:$J$13,'EVM - Valor Agregado'!$A$2:$A$13,$A3,'EVM - Valor Agregado'!$B$2:$B$13,_xlfn.MAXIFS('EVM - Valor Agregado'!$B$2:$B$13,'EVM - Valor Agregado'!$A$2:$A$13,$A3,'EVM - Valor Agregado'!$G$2:$G$13,"<>"))) | I3: =IF(_xlfn.MAXIFS('EVM - Valor Agregado'!$B$2:$B$13,'EVM - Valor Agregado'!$A$2:$A$13,$A3,'EVM - Valor Agregado'!$G$2:$G$13,"<>")=0,"",SUMIFS('EVM - Valor Agregado'!$K$2:$K$13,'EVM - Valor Agregado'!$A$2:$A$13,$A3,'EVM - Valor Agregado'!$B$2:$B$13,_xlfn.MAXIFS('EVM - Valor Agregado'!$B$2:$B$13,'EVM - Valor Agregado'!$A$2:$A$13,$A3,'EVM - Valor Agregado'!$G$2:$G$13,"<>"))) | J3: =SUMPRODUCT((Planejamento!$B$1:$O$1>=C3)*(Planejamento!$B$1:$O$1<=D3)*Planejamento!$B$33:$O$33) | K3: =IF(_xlfn.MAXIFS('EVM - Valor Agregado'!$B$2:$B$13,'EVM - Valor Agregado'!$A$2:$A$13,$A3,'EVM - Valor Agregado'!$G$2:$G$13,"<>")=0,"",SUMIFS('EVM - Valor Agregado'!$P$2:$P$13,'EVM - Valor Agregado'!$A$2:$A$13,$A3,'EVM - Valor Agregado'!$B$2:$B$13,_xlfn.MAXIFS('EVM - Valor Agregado'!$B$2:$B$13,'EVM - Valor Agregado'!$A$2:$A$13,$A3,'EVM - Valor Agregado'!$G$2:$G$13,"<>"))) | L3: =IF(_xlfn.MAXIFS('EVM - Valor Agregado'!$B$2:$B$13,'EVM - Valor Agregado'!$A$2:$A$13,$A3,'EVM - Valor Agregado'!$G$2:$G$13,"<>")=0,"",SUMIFS('EVM - Valor Agregado'!$U$2:$U$13,'EVM - Valor Agregado'!$A$2:$A$13,$A3,'EVM - Valor Agregado'!$B$2:$B$13,_xlfn.MAXIFS('EVM - Valor Agregado'!$B$2:$B$13,'EVM - Valor Agregado'!$A$2:$A$13,$A3,'EVM - Valor Agregado'!$G$2:$G$13,"<>"))) | M3: =IF(_xlfn.MAXIFS('EVM - Valor Agregado'!$B$2:$B$13,'EVM - Valor Agregado'!$A$2:$A$13,$A3,'EVM - Valor Agregado'!$G$2:$G$13,"<>")=0,"",SUMIFS('EVM - Valor Agregado'!$S$2:$S$13,'EVM - Valor Agregado'!$A$2:$A$13,$A3,'EVM - Valor Agregado'!$B$2:$B$13,_xlfn.MAXIFS('EVM - Valor Agregado'!$B$2:$B$13,'EVM - Valor Agregado'!$A$2:$A$13,$A3,'EVM - Valor Agregado'!$G$2:$G$13,"<>"))) | N3: =IF(OR(K3="",K3=0),"",L3/K3) | O3: =IF(OR(M3="",M3=0),"",L3/M3) | P3: =IF(OR(N3="",N3=0),"",C3+(D3-C3+1)/N3) | Q3: Congelar o PRP na planning de 28/09.
A4: R3 | B4: 46356 | C4: =_xlfn.MINIFS('EVM - Valor Agregado'!$C$2:$C$13,'EVM - Valor Agregado'!$A$2:$A$13,$A4) | D4: =_xlfn.MAXIFS('EVM - Valor Agregado'!$D$2:$D$13,'EVM - Valor Agregado'!$A$2:$A$13,$A4) | E4: =COUNTIF('EVM - Valor Agregado'!$A$2:$A$13,$A4) | F4: =SUMIFS('EVM - Valor Agregado'!$E$2:$E$13,'EVM - Valor Agregado'!$A$2:$A$13,$A4) | H4: =IF(_xlfn.MAXIFS('EVM - Valor Agregado'!$B$2:$B$13,'EVM - Valor Agregado'!$A$2:$A$13,$A4,'EVM - Valor Agregado'!$G$2:$G$13,"<>")=0,"",SUMIFS('EVM - Valor Agregado'!$J$2:$J$13,'EVM - Valor Agregado'!$A$2:$A$13,$A4,'EVM - Valor Agregado'!$B$2:$B$13,_xlfn.MAXIFS('EVM - Valor Agregado'!$B$2:$B$13,'EVM - Valor Agregado'!$A$2:$A$13,$A4,'EVM - Valor Agregado'!$G$2:$G$13,"<>"))) | I4: =IF(_xlfn.MAXIFS('EVM - Valor Agregado'!$B$2:$B$13,'EVM - Valor Agregado'!$A$2:$A$13,$A4,'EVM - Valor Agregado'!$G$2:$G$13,"<>")=0,"",SUMIFS('EVM - Valor Agregado'!$K$2:$K$13,'EVM - Valor Agregado'!$A$2:$A$13,$A4,'EVM - Valor Agregado'!$B$2:$B$13,_xlfn.MAXIFS('EVM - Valor Agregado'!$B$2:$B$13,'EVM - Valor Agregado'!$A$2:$A$13,$A4,'EVM - Valor Agregado'!$G$2:$G$13,"<>"))) | J4: =SUMPRODUCT((Planejamento!$B$1:$O$1>=C4)*(Planejamento!$B$1:$O$1<=D4)*Planejamento!$B$33:$O$33) | K4: =IF(_xlfn.MAXIFS('EVM - Valor Agregado'!$B$2:$B$13,'EVM - Valor Agregado'!$A$2:$A$13,$A4,'EVM - Valor Agregado'!$G$2:$G$13,"<>")=0,"",SUMIFS('EVM - Valor Agregado'!$P$2:$P$13,'EVM - Valor Agregado'!$A$2:$A$13,$A4,'EVM - Valor Agregado'!$B$2:$B$13,_xlfn.MAXIFS('EVM - Valor Agregado'!$B$2:$B$13,'EVM - Valor Agregado'!$A$2:$A$13,$A4,'EVM - Valor Agregado'!$G$2:$G$13,"<>"))) | L4: =IF(_xlfn.MAXIFS('EVM - Valor Agregado'!$B$2:$B$13,'EVM - Valor Agregado'!$A$2:$A$13,$A4,'EVM - Valor Agregado'!$G$2:$G$13,"<>")=0,"",SUMIFS('EVM - Valor Agregado'!$U$2:$U$13,'EVM - Valor Agregado'!$A$2:$A$13,$A4,'EVM - Valor Agregado'!$B$2:$B$13,_xlfn.MAXIFS('EVM - Valor Agregado'!$B$2:$B$13,'EVM - Valor Agregado'!$A$2:$A$13,$A4,'EVM - Valor Agregado'!$G$2:$G$13,"<>"))) | M4: =IF(_xlfn.MAXIFS('EVM - Valor Agregado'!$B$2:$B$13,'EVM - Valor Agregado'!$A$2:$A$13,$A4,'EVM - Valor Agregado'!$G$2:$G$13,"<>")=0,"",SUMIFS('EVM - Valor Agregado'!$S$2:$S$13,'EVM - Valor Agregado'!$A$2:$A$13,$A4,'EVM - Valor Agregado'!$B$2:$B$13,_xlfn.MAXIFS('EVM - Valor Agregado'!$B$2:$B$13,'EVM - Valor Agregado'!$A$2:$A$13,$A4,'EVM - Valor Agregado'!$G$2:$G$13,"<>"))) | N4: =IF(OR(K4="",K4=0),"",L4/K4) | O4: =IF(OR(M4="",M4=0),"",L4/M4) | P4: =IF(OR(N4="",N4=0),"",C4+(D4-C4+1)/N4) | Q4: Congelar o PRP na planning de 26/10.
A5: Total | E5: =SUM(E2:E4) | F5: =SUM(F2:F4) | J5: =SUM(J2:J4)
A7: Fórmulas (Sulaiman, Barton & Blackburn, 2006 — AgileEVM):
A8: PPC = semanas decorridas da release ÷ semanas da release (é o n/L do artigo, ponderado porque as sprints 1 e 2 têm 2 semanas)
A9: APC = RPC ÷ PRP PV = PPC × BAC EV = APC × BAC AC = custo real acumulado (horas × custo/hora; sem horas, custo planejado)
A10: SPI = EV ÷ PV CPI = EV ÷ AC SV = EV − PV CV = EV − AC ETC = (BAC − EV) ÷ CPI EAC = AC + ETC
A11: RD (término estimado) = início da release + duração ÷ SPI

Sheet EVM - Valor Agregado
A1: Release | B1: Sprint (n) | C1: Início da sprint | D1: Fim da sprint | E1: Semanas | F1: Issues | G1: Pontos planejados (PP) | H1: Pontos concluídos (PC) | I1: Pontos adicionados (PA) | J1: Planned Release Points (PRP) | K1: Release Points Completed (RPC) | L1: Actual Percent Complete (APC) | M1: Planned Percent Complete (PPC) | N1: Budget at Completion (BAC) | O1: Sprint Cost (SC) | P1: Planned Value (PV) | Q1: Horas reais | R1: Custo da sprint | S1: Actual Cost (AC) | T1: Origem do AC | U1: Earned Value (EV) | V1: Cost Variance (CV) | W1: Schedule Variance (SV) | X1: Cost Performance Index (CPI) | Y1: Schedule Performance Index (SPI) | Z1: Estimate to Complete (ETC) | AA1: Estimate at Completion (EAC) | AB1: Release Date (RD)
A2: R1 | B2: 1 | C2: 46258 | D2: 46271 | E2: =(D2-C2+1)/7 | F2: DOC#15, DOC#38 | G2: 6 | H2: 1 | I2: 0 | J2: =IF($G2="","",SUMIFS('Sumário EVM'!$G$2:$G$4,'Sumário EVM'!$A$2:$A$4,$A2)+SUMIFS($I$2:$I$13,$A$2:$A$13,$A2,$B$2:$B$13,"<="&$B2)) | K2: =IF($G2="","",SUMIFS($H$2:$H$13,$A$2:$A$13,$A2,$B$2:$B$13,"<="&$B2)) | L2: =IF(OR($G2="",J2=0),"",K2/J2) | M2: =SUMIFS($E$2:$E$13,$A$2:$A$13,$A2,$B$2:$B$13,"<="&$B2)/SUMIFS($E$2:$E$13,$A$2:$A$13,$A2) | N2: =SUMIFS('Sumário EVM'!$J$2:$J$4,'Sumário EVM'!$A$2:$A$4,$A2) | O2: =SUMPRODUCT((Planejamento!$B$1:$O$1>=C2)*(Planejamento!$B$1:$O$1<=D2)*Planejamento!$B$33:$O$33) | P2: =M2*N2 | Q2: =SUMIFS(Horas!$C$2:$C$1000,Horas!$A$2:$A$1000,B2) | R2: =IF(Q2>0,Q2*Custos!$D$25,O2) | S2: =IF($G2="","",SUMIFS($R$2:$R$13,$A$2:$A$13,$A2,$B$2:$B$13,"<="&$B2)) | T2: =IF($G2="","",IF(Q2>0,"horas reais","estimado (custo planejado)")) | U2: =IF(L2="","",L2*N2) | V2: =IF(U2="","",U2-S2) | W2: =IF(U2="","",U2-P2) | X2: =IF(OR(U2="",S2=0),"",U2/S2) | Y2: =IF(OR(U2="",P2=0),"",U2/P2) | Z2: =IF(OR(X2="",X2=0),"",(N2-U2)/X2) | AA2: =IF(Z2="","",S2+Z2) | AB2: =IF(OR(Y2="",Y2=0),"",_xlfn.MINIFS($C$2:$C$13,$A$2:$A$13,$A2)+(_xlfn.MAXIFS($D$2:$D$13,$A$2:$A$13,$A2)-_xlfn.MINIFS($C$2:$C$13,$A$2:$A$13,$A2)+1)/Y2)
A3: R1 | B3: 2 | C3: 46272 | D3: 46285 | E3: =(D3-C3+1)/7 | F3: DOC#1, #3, #11, #17, #18, #38; Service#3 | G3: 17 | H3: 0 | I3: 12 | J3: =IF($G3="","",SUMIFS('Sumário EVM'!$G$2:$G$4,'Sumário EVM'!$A$2:$A$4,$A3)+SUMIFS($I$2:$I$13,$A$2:$A$13,$A3,$B$2:$B$13,"<="&$B3)) | K3: =IF($G3="","",SUMIFS($H$2:$H$13,$A$2:$A$13,$A3,$B$2:$B$13,"<="&$B3)) | L3: =IF(OR($G3="",J3=0),"",K3/J3) | M3: =SUMIFS($E$2:$E$13,$A$2:$A$13,$A3,$B$2:$B$13,"<="&$B3)/SUMIFS($E$2:$E$13,$A$2:$A$13,$A3) | N3: =SUMIFS('Sumário EVM'!$J$2:$J$4,'Sumário EVM'!$A$2:$A$4,$A3) | O3: =SUMPRODUCT((Planejamento!$B$1:$O$1>=C3)*(Planejamento!$B$1:$O$1<=D3)*Planejamento!$B$33:$O$33) | P3: =M3*N3 | Q3: =SUMIFS(Horas!$C$2:$C$1000,Horas!$A$2:$A$1000,B3) | R3: =IF(Q3>0,Q3*Custos!$D$25,O3) | S3: =IF($G3="","",SUMIFS($R$2:$R$13,$A$2:$A$13,$A3,$B$2:$B$13,"<="&$B3)) | T3: =IF($G3="","",IF(Q3>0,"horas reais","estimado (custo planejado)")) | U3: =IF(L3="","",L3*N3) | V3: =IF(U3="","",U3-S3) | W3: =IF(U3="","",U3-P3) | X3: =IF(OR(U3="",S3=0),"",U3/S3) | Y3: =IF(OR(U3="",P3=0),"",U3/P3) | Z3: =IF(OR(X3="",X3=0),"",(N3-U3)/X3) | AA3: =IF(Z3="","",S3+Z3) | AB3: =IF(OR(Y3="",Y3=0),"",_xlfn.MINIFS($C$2:$C$13,$A$2:$A$13,$A3)+(_xlfn.MAXIFS($D$2:$D$13,$A$2:$A$13,$A3)-_xlfn.MINIFS($C$2:$C$13,$A$2:$A$13,$A3)+1)/Y3)
A4: R1 | B4: 3 | C4: 46286 | D4: 46292 | E4: =(D4-C4+1)/7 | F4: 45 issues (ver sprint Sep 21-27 no Zenhub) | G4: 132 | H4: 10 | I4: 115 | J4: =IF($G4="","",SUMIFS('Sumário EVM'!$G$2:$G$4,'Sumário EVM'!$A$2:$A$4,$A4)+SUMIFS($I$2:$I$13,$A$2:$A$13,$A4,$B$2:$B$13,"<="&$B4)) | K4: =IF($G4="","",SUMIFS($H$2:$H$13,$A$2:$A$13,$A4,$B$2:$B$13,"<="&$B4)) | L4: =IF(OR($G4="",J4=0),"",K4/J4) | M4: =SUMIFS($E$2:$E$13,$A$2:$A$13,$A4,$B$2:$B$13,"<="&$B4)/SUMIFS($E$2:$E$13,$A$2:$A$13,$A4) | N4: =SUMIFS('Sumário EVM'!$J$2:$J$4,'Sumário EVM'!$A$2:$A$4,$A4) | O4: =SUMPRODUCT((Planejamento!$B$1:$O$1>=C4)*(Planejamento!$B$1:$O$1<=D4)*Planejamento!$B$33:$O$33) | P4: =M4*N4 | Q4: =SUMIFS(Horas!$C$2:$C$1000,Horas!$A$2:$A$1000,B4) | R4: =IF(Q4>0,Q4*Custos!$D$25,O4) | S4: =IF($G4="","",SUMIFS($R$2:$R$13,$A$2:$A$13,$A4,$B$2:$B$13,"<="&$B4)) | T4: =IF($G4="","",IF(Q4>0,"horas reais","estimado (custo planejado)")) | U4: =IF(L4="","",L4*N4) | V4: =IF(U4="","",U4-S4) | W4: =IF(U4="","",U4-P4) | X4: =IF(OR(U4="",S4=0),"",U4/S4) | Y4: =IF(OR(U4="",P4=0),"",U4/P4) | Z4: =IF(OR(X4="",X4=0),"",(N4-U4)/X4) | AA4: =IF(Z4="","",S4+Z4) | AB4: =IF(OR(Y4="",Y4=0),"",_xlfn.MINIFS($C$2:$C$13,$A$2:$A$13,$A4)+(_xlfn.MAXIFS($D$2:$D$13,$A$2:$A$13,$A4)-_xlfn.MINIFS($C$2:$C$13,$A$2:$A$13,$A4)+1)/Y4)
A5: R2 | B5: 4 | C5: 46293 | D5: 46299 | E5: =(D5-C5+1)/7 | J5: =IF($G5="","",SUMIFS('Sumário EVM'!$G$2:$G$4,'Sumário EVM'!$A$2:$A$4,$A5)+SUMIFS($I$2:$I$13,$A$2:$A$13,$A5,$B$2:$B$13,"<="&$B5)) | K5: =IF($G5="","",SUMIFS($H$2:$H$13,$A$2:$A$13,$A5,$B$2:$B$13,"<="&$B5)) | L5: =IF(OR($G5="",J5=0),"",K5/J5) | M5: =SUMIFS($E$2:$E$13,$A$2:$A$13,$A5,$B$2:$B$13,"<="&$B5)/SUMIFS($E$2:$E$13,$A$2:$A$13,$A5) | N5: =SUMIFS('Sumário EVM'!$J$2:$J$4,'Sumário EVM'!$A$2:$A$4,$A5) | O5: =SUMPRODUCT((Planejamento!$B$1:$O$1>=C5)*(Planejamento!$B$1:$O$1<=D5)*Planejamento!$B$33:$O$33) | P5: =M5*N5 | Q5: =SUMIFS(Horas!$C$2:$C$1000,Horas!$A$2:$A$1000,B5) | R5: =IF(Q5>0,Q5*Custos!$D$25,O5) | S5: =IF($G5="","",SUMIFS($R$2:$R$13,$A$2:$A$13,$A5,$B$2:$B$13,"<="&$B5)) | T5: =IF($G5="","",IF(Q5>0,"horas reais","estimado (custo planejado)")) | U5: =IF(L5="","",L5*N5) | V5: =IF(U5="","",U5-S5) | W5: =IF(U5="","",U5-P5) | X5: =IF(OR(U5="",S5=0),"",U5/S5) | Y5: =IF(OR(U5="",P5=0),"",U5/P5) | Z5: =IF(OR(X5="",X5=0),"",(N5-U5)/X5) | AA5: =IF(Z5="","",S5+Z5) | AB5: =IF(OR(Y5="",Y5=0),"",_xlfn.MINIFS($C$2:$C$13,$A$2:$A$13,$A5)+(_xlfn.MAXIFS($D$2:$D$13,$A$2:$A$13,$A5)-_xlfn.MINIFS($C$2:$C$13,$A$2:$A$13,$A5)+1)/Y5)
A6: R2 | B6: 5 | C6: 46300 | D6: 46306 | E6: =(D6-C6+1)/7 | J6: =IF($G6="","",SUMIFS('Sumário EVM'!$G$2:$G$4,'Sumário EVM'!$A$2:$A$4,$A6)+SUMIFS($I$2:$I$13,$A$2:$A$13,$A6,$B$2:$B$13,"<="&$B6)) | K6: =IF($G6="","",SUMIFS($H$2:$H$13,$A$2:$A$13,$A6,$B$2:$B$13,"<="&$B6)) | L6: =IF(OR($G6="",J6=0),"",K6/J6) | M6: =SUMIFS($E$2:$E$13,$A$2:$A$13,$A6,$B$2:$B$13,"<="&$B6)/SUMIFS($E$2:$E$13,$A$2:$A$13,$A6) | N6: =SUMIFS('Sumário EVM'!$J$2:$J$4,'Sumário EVM'!$A$2:$A$4,$A6) | O6: =SUMPRODUCT((Planejamento!$B$1:$O$1>=C6)*(Planejamento!$B$1:$O$1<=D6)*Planejamento!$B$33:$O$33) | P6: =M6*N6 | Q6: =SUMIFS(Horas!$C$2:$C$1000,Horas!$A$2:$A$1000,B6) | R6: =IF(Q6>0,Q6*Custos!$D$25,O6) | S6: =IF($G6="","",SUMIFS($R$2:$R$13,$A$2:$A$13,$A6,$B$2:$B$13,"<="&$B6)) | T6: =IF($G6="","",IF(Q6>0,"horas reais","estimado (custo planejado)")) | U6: =IF(L6="","",L6*N6) | V6: =IF(U6="","",U6-S6) | W6: =IF(U6="","",U6-P6) | X6: =IF(OR(U6="",S6=0),"",U6/S6) | Y6: =IF(OR(U6="",P6=0),"",U6/P6) | Z6: =IF(OR(X6="",X6=0),"",(N6-U6)/X6) | AA6: =IF(Z6="","",S6+Z6) | AB6: =IF(OR(Y6="",Y6=0),"",_xlfn.MINIFS($C$2:$C$13,$A$2:$A$13,$A6)+(_xlfn.MAXIFS($D$2:$D$13,$A$2:$A$13,$A6)-_xlfn.MINIFS($C$2:$C$13,$A$2:$A$13,$A6)+1)/Y6)
A7: R2 | B7: 6 | C7: 46307 | D7: 46313 | E7: =(D7-C7+1)/7 | J7: =IF($G7="","",SUMIFS('Sumário EVM'!$G$2:$G$4,'Sumário EVM'!$A$2:$A$4,$A7)+SUMIFS($I$2:$I$13,$A$2:$A$13,$A7,$B$2:$B$13,"<="&$B7)) | K7: =IF($G7="","",SUMIFS($H$2:$H$13,$A$2:$A$13,$A7,$B$2:$B$13,"<="&$B7)) | L7: =IF(OR($G7="",J7=0),"",K7/J7) | M7: =SUMIFS($E$2:$E$13,$A$2:$A$13,$A7,$B$2:$B$13,"<="&$B7)/SUMIFS($E$2:$E$13,$A$2:$A$13,$A7) | N7: =SUMIFS('Sumário EVM'!$J$2:$J$4,'Sumário EVM'!$A$2:$A$4,$A7) | O7: =SUMPRODUCT((Planejamento!$B$1:$O$1>=C7)*(Planejamento!$B$1:$O$1<=D7)*Planejamento!$B$33:$O$33) | P7: =M7*N7 | Q7: =SUMIFS(Horas!$C$2:$C$1000,Horas!$A$2:$A$1000,B7) | R7: =IF(Q7>0,Q7*Custos!$D$25,O7) | S7: =IF($G7="","",SUMIFS($R$2:$R$13,$A$2:$A$13,$A7,$B$2:$B$13,"<="&$B7)) | T7: =IF($G7="","",IF(Q7>0,"horas reais","estimado (custo planejado)")) | U7: =IF(L7="","",L7*N7) | V7: =IF(U7="","",U7-S7) | W7: =IF(U7="","",U7-P7) | X7: =IF(OR(U7="",S7=0),"",U7/S7) | Y7: =IF(OR(U7="",P7=0),"",U7/P7) | Z7: =IF(OR(X7="",X7=0),"",(N7-U7)/X7) | AA7: =IF(Z7="","",S7+Z7) | AB7: =IF(OR(Y7="",Y7=0),"",_xlfn.MINIFS($C$2:$C$13,$A$2:$A$13,$A7)+(_xlfn.MAXIFS($D$2:$D$13,$A$2:$A$13,$A7)-_xlfn.MINIFS($C$2:$C$13,$A$2:$A$13,$A7)+1)/Y7)
A8: R2 | B8: 7 | C8: 46314 | D8: 46320 | E8: =(D8-C8+1)/7 | J8: =IF($G8="","",SUMIFS('Sumário EVM'!$G$2:$G$4,'Sumário EVM'!$A$2:$A$4,$A8)+SUMIFS($I$2:$I$13,$A$2:$A$13,$A8,$B$2:$B$13,"<="&$B8)) | K8: =IF($G8="","",SUMIFS($H$2:$H$13,$A$2:$A$13,$A8,$B$2:$B$13,"<="&$B8)) | L8: =IF(OR($G8="",J8=0),"",K8/J8) | M8: =SUMIFS($E$2:$E$13,$A$2:$A$13,$A8,$B$2:$B$13,"<="&$B8)/SUMIFS($E$2:$E$13,$A$2:$A$13,$A8) | N8: =SUMIFS('Sumário EVM'!$J$2:$J$4,'Sumário EVM'!$A$2:$A$4,$A8) | O8: =SUMPRODUCT((Planejamento!$B$1:$O$1>=C8)*(Planejamento!$B$1:$O$1<=D8)*Planejamento!$B$33:$O$33) | P8: =M8*N8 | Q8: =SUMIFS(Horas!$C$2:$C$1000,Horas!$A$2:$A$1000,B8) | R8: =IF(Q8>0,Q8*Custos!$D$25,O8) | S8: =IF($G8="","",SUMIFS($R$2:$R$13,$A$2:$A$13,$A8,$B$2:$B$13,"<="&$B8)) | T8: =IF($G8="","",IF(Q8>0,"horas reais","estimado (custo planejado)")) | U8: =IF(L8="","",L8*N8) | V8: =IF(U8="","",U8-S8) | W8: =IF(U8="","",U8-P8) | X8: =IF(OR(U8="",S8=0),"",U8/S8) | Y8: =IF(OR(U8="",P8=0),"",U8/P8) | Z8: =IF(OR(X8="",X8=0),"",(N8-U8)/X8) | AA8: =IF(Z8="","",S8+Z8) | AB8: =IF(OR(Y8="",Y8=0),"",_xlfn.MINIFS($C$2:$C$13,$A$2:$A$13,$A8)+(_xlfn.MAXIFS($D$2:$D$13,$A$2:$A$13,$A8)-_xlfn.MINIFS($C$2:$C$13,$A$2:$A$13,$A8)+1)/Y8)
A9: R3 | B9: 8 | C9: 46321 | D9: 46327 | E9: =(D9-C9+1)/7 | J9: =IF($G9="","",SUMIFS('Sumário EVM'!$G$2:$G$4,'Sumário EVM'!$A$2:$A$4,$A9)+SUMIFS($I$2:$I$13,$A$2:$A$13,$A9,$B$2:$B$13,"<="&$B9)) | K9: =IF($G9="","",SUMIFS($H$2:$H$13,$A$2:$A$13,$A9,$B$2:$B$13,"<="&$B9)) | L9: =IF(OR($G9="",J9=0),"",K9/J9) | M9: =SUMIFS($E$2:$E$13,$A$2:$A$13,$A9,$B$2:$B$13,"<="&$B9)/SUMIFS($E$2:$E$13,$A$2:$A$13,$A9) | N9: =SUMIFS('Sumário EVM'!$J$2:$J$4,'Sumário EVM'!$A$2:$A$4,$A9) | O9: =SUMPRODUCT((Planejamento!$B$1:$O$1>=C9)*(Planejamento!$B$1:$O$1<=D9)*Planejamento!$B$33:$O$33) | P9: =M9*N9 | Q9: =SUMIFS(Horas!$C$2:$C$1000,Horas!$A$2:$A$1000,B9) | R9: =IF(Q9>0,Q9*Custos!$D$25,O9) | S9: =IF($G9="","",SUMIFS($R$2:$R$13,$A$2:$A$13,$A9,$B$2:$B$13,"<="&$B9)) | T9: =IF($G9="","",IF(Q9>0,"horas reais","estimado (custo planejado)")) | U9: =IF(L9="","",L9*N9) | V9: =IF(U9="","",U9-S9) | W9: =IF(U9="","",U9-P9) | X9: =IF(OR(U9="",S9=0),"",U9/S9) | Y9: =IF(OR(U9="",P9=0),"",U9/P9) | Z9: =IF(OR(X9="",X9=0),"",(N9-U9)/X9) | AA9: =IF(Z9="","",S9+Z9) | AB9: =IF(OR(Y9="",Y9=0),"",_xlfn.MINIFS($C$2:$C$13,$A$2:$A$13,$A9)+(_xlfn.MAXIFS($D$2:$D$13,$A$2:$A$13,$A9)-_xlfn.MINIFS($C$2:$C$13,$A$2:$A$13,$A9)+1)/Y9)
A10: R3 | B10: 9 | C10: 46328 | D10: 46334 | E10: =(D10-C10+1)/7 | J10: =IF($G10="","",SUMIFS('Sumário EVM'!$G$2:$G$4,'Sumário EVM'!$A$2:$A$4,$A10)+SUMIFS($I$2:$I$13,$A$2:$A$13,$A10,$B$2:$B$13,"<="&$B10)) | K10: =IF($G10="","",SUMIFS($H$2:$H$13,$A$2:$A$13,$A10,$B$2:$B$13,"<="&$B10)) | L10: =IF(OR($G10="",J10=0),"",K10/J10) | M10: =SUMIFS($E$2:$E$13,$A$2:$A$13,$A10,$B$2:$B$13,"<="&$B10)/SUMIFS($E$2:$E$13,$A$2:$A$13,$A10) | N10: =SUMIFS('Sumário EVM'!$J$2:$J$4,'Sumário EVM'!$A$2:$A$4,$A10) | O10: =SUMPRODUCT((Planejamento!$B$1:$O$1>=C10)*(Planejamento!$B$1:$O$1<=D10)*Planejamento!$B$33:$O$33) | P10: =M10*N10 | Q10: =SUMIFS(Horas!$C$2:$C$1000,Horas!$A$2:$A$1000,B10) | R10: =IF(Q10>0,Q10*Custos!$D$25,O10) | S10: =IF($G10="","",SUMIFS($R$2:$R$13,$A$2:$A$13,$A10,$B$2:$B$13,"<="&$B10)) | T10: =IF($G10="","",IF(Q10>0,"horas reais","estimado (custo planejado)")) | U10: =IF(L10="","",L10*N10) | V10: =IF(U10="","",U10-S10) | W10: =IF(U10="","",U10-P10) | X10: =IF(OR(U10="",S10=0),"",U10/S10) | Y10: =IF(OR(U10="",P10=0),"",U10/P10) | Z10: =IF(OR(X10="",X10=0),"",(N10-U10)/X10) | AA10: =IF(Z10="","",S10+Z10) | AB10: =IF(OR(Y10="",Y10=0),"",_xlfn.MINIFS($C$2:$C$13,$A$2:$A$13,$A10)+(_xlfn.MAXIFS($D$2:$D$13,$A$2:$A$13,$A10)-_xlfn.MINIFS($C$2:$C$13,$A$2:$A$13,$A10)+1)/Y10)
A11: R3 | B11: 10 | C11: 46335 | D11: 46341 | E11: =(D11-C11+1)/7 | J11: =IF($G11="","",SUMIFS('Sumário EVM'!$G$2:$G$4,'Sumário EVM'!$A$2:$A$4,$A11)+SUMIFS($I$2:$I$13,$A$2:$A$13,$A11,$B$2:$B$13,"<="&$B11)) | K11: =IF($G11="","",SUMIFS($H$2:$H$13,$A$2:$A$13,$A11,$B$2:$B$13,"<="&$B11)) | L11: =IF(OR($G11="",J11=0),"",K11/J11) | M11: =SUMIFS($E$2:$E$13,$A$2:$A$13,$A11,$B$2:$B$13,"<="&$B11)/SUMIFS($E$2:$E$13,$A$2:$A$13,$A11) | N11: =SUMIFS('Sumário EVM'!$J$2:$J$4,'Sumário EVM'!$A$2:$A$4,$A11) | O11: =SUMPRODUCT((Planejamento!$B$1:$O$1>=C11)*(Planejamento!$B$1:$O$1<=D11)*Planejamento!$B$33:$O$33) | P11: =M11*N11 | Q11: =SUMIFS(Horas!$C$2:$C$1000,Horas!$A$2:$A$1000,B11) | R11: =IF(Q11>0,Q11*Custos!$D$25,O11) | S11: =IF($G11="","",SUMIFS($R$2:$R$13,$A$2:$A$13,$A11,$B$2:$B$13,"<="&$B11)) | T11: =IF($G11="","",IF(Q11>0,"horas reais","estimado (custo planejado)")) | U11: =IF(L11="","",L11*N11) | V11: =IF(U11="","",U11-S11) | W11: =IF(U11="","",U11-P11) | X11: =IF(OR(U11="",S11=0),"",U11/S11) | Y11: =IF(OR(U11="",P11=0),"",U11/P11) | Z11: =IF(OR(X11="",X11=0),"",(N11-U11)/X11) | AA11: =IF(Z11="","",S11+Z11) | AB11: =IF(OR(Y11="",Y11=0),"",_xlfn.MINIFS($C$2:$C$13,$A$2:$A$13,$A11)+(_xlfn.MAXIFS($D$2:$D$13,$A$2:$A$13,$A11)-_xlfn.MINIFS($C$2:$C$13,$A$2:$A$13,$A11)+1)/Y11)
A12: R3 | B12: 11 | C12: 46342 | D12: 46348 | E12: =(D12-C12+1)/7 | J12: =IF($G12="","",SUMIFS('Sumário EVM'!$G$2:$G$4,'Sumário EVM'!$A$2:$A$4,$A12)+SUMIFS($I$2:$I$13,$A$2:$A$13,$A12,$B$2:$B$13,"<="&$B12)) | K12: =IF($G12="","",SUMIFS($H$2:$H$13,$A$2:$A$13,$A12,$B$2:$B$13,"<="&$B12)) | L12: =IF(OR($G12="",J12=0),"",K12/J12) | M12: =SUMIFS($E$2:$E$13,$A$2:$A$13,$A12,$B$2:$B$13,"<="&$B12)/SUMIFS($E$2:$E$13,$A$2:$A$13,$A12) | N12: =SUMIFS('Sumário EVM'!$J$2:$J$4,'Sumário EVM'!$A$2:$A$4,$A12) | O12: =SUMPRODUCT((Planejamento!$B$1:$O$1>=C12)*(Planejamento!$B$1:$O$1<=D12)*Planejamento!$B$33:$O$33) | P12: =M12*N12 | Q12: =SUMIFS(Horas!$C$2:$C$1000,Horas!$A$2:$A$1000,B12) | R12: =IF(Q12>0,Q12*Custos!$D$25,O12) | S12: =IF($G12="","",SUMIFS($R$2:$R$13,$A$2:$A$13,$A12,$B$2:$B$13,"<="&$B12)) | T12: =IF($G12="","",IF(Q12>0,"horas reais","estimado (custo planejado)")) | U12: =IF(L12="","",L12*N12) | V12: =IF(U12="","",U12-S12) | W12: =IF(U12="","",U12-P12) | X12: =IF(OR(U12="",S12=0),"",U12/S12) | Y12: =IF(OR(U12="",P12=0),"",U12/P12) | Z12: =IF(OR(X12="",X12=0),"",(N12-U12)/X12) | AA12: =IF(Z12="","",S12+Z12) | AB12: =IF(OR(Y12="",Y12=0),"",_xlfn.MINIFS($C$2:$C$13,$A$2:$A$13,$A12)+(_xlfn.MAXIFS($D$2:$D$13,$A$2:$A$13,$A12)-_xlfn.MINIFS($C$2:$C$13,$A$2:$A$13,$A12)+1)/Y12)
A13: R3 | B13: 12 | C13: 46349 | D13: 46355 | E13: =(D13-C13+1)/7 | J13: =IF($G13="","",SUMIFS('Sumário EVM'!$G$2:$G$4,'Sumário EVM'!$A$2:$A$4,$A13)+SUMIFS($I$2:$I$13,$A$2:$A$13,$A13,$B$2:$B$13,"<="&$B13)) | K13: =IF($G13="","",SUMIFS($H$2:$H$13,$A$2:$A$13,$A13,$B$2:$B$13,"<="&$B13)) | L13: =IF(OR($G13="",J13=0),"",K13/J13) | M13: =SUMIFS($E$2:$E$13,$A$2:$A$13,$A13,$B$2:$B$13,"<="&$B13)/SUMIFS($E$2:$E$13,$A$2:$A$13,$A13) | N13: =SUMIFS('Sumário EVM'!$J$2:$J$4,'Sumário EVM'!$A$2:$A$4,$A13) | O13: =SUMPRODUCT((Planejamento!$B$1:$O$1>=C13)*(Planejamento!$B$1:$O$1<=D13)*Planejamento!$B$33:$O$33) | P13: =M13*N13 | Q13: =SUMIFS(Horas!$C$2:$C$1000,Horas!$A$2:$A$1000,B13) | R13: =IF(Q13>0,Q13*Custos!$D$25,O13) | S13: =IF($G13="","",SUMIFS($R$2:$R$13,$A$2:$A$13,$A13,$B$2:$B$13,"<="&$B13)) | T13: =IF($G13="","",IF(Q13>0,"horas reais","estimado (custo planejado)")) | U13: =IF(L13="","",L13*N13) | V13: =IF(U13="","",U13-S13) | W13: =IF(U13="","",U13-P13) | X13: =IF(OR(U13="",S13=0),"",U13/S13) | Y13: =IF(OR(U13="",P13=0),"",U13/P13) | Z13: =IF(OR(X13="",X13=0),"",(N13-U13)/X13) | AA13: =IF(Z13="","",S13+Z13) | AB13: =IF(OR(Y13="",Y13=0),"",_xlfn.MINIFS($C$2:$C$13,$A$2:$A$13,$A13)+(_xlfn.MAXIFS($D$2:$D$13,$A$2:$A$13,$A13)-_xlfn.MINIFS($C$2:$C$13,$A$2:$A$13,$A13)+1)/Y13)
A15: Amarelo: preencher ao fim de cada sprint com os números do Zenhub (o dashboard mostra os valores prontos na aba Velocity e Burndown → Conferência com o Zenhub). Azul-claro: calculado.

Sheet EVM - Velocity
A1: Sprint | B1: Release | C1: Semanas | D1: Pontos planejados (PP) | E1: Pontos concluídos (PC) | F1: Velocity | G1: Pontos por semana | H1: Velocity média | I1: Taxa de conclusão
A2: ='EVM - Valor Agregado'!B2 | B2: ='EVM - Valor Agregado'!A2 | C2: ='EVM - Valor Agregado'!E2 | D2: =IF('EVM - Valor Agregado'!G2="","",'EVM - Valor Agregado'!G2) | E2: =IF('EVM - Valor Agregado'!G2="","",'EVM - Valor Agregado'!H2) | F2: =E2 | G2: =IF(E2="","",E2/C2) | H2: =IF(G2="","",AVERAGE($G$2:G2)) | I2: =IF(OR(D2="",D2=0),"",E2/D2)
A3: ='EVM - Valor Agregado'!B3 | B3: ='EVM - Valor Agregado'!A3 | C3: ='EVM - Valor Agregado'!E3 | D3: =IF('EVM - Valor Agregado'!G3="","",'EVM - Valor Agregado'!G3) | E3: =IF('EVM - Valor Agregado'!G3="","",'EVM - Valor Agregado'!H3) | F3: =E3 | G3: =IF(E3="","",E3/C3) | H3: =IF(G3="","",AVERAGE($G$2:G3)) | I3: =IF(OR(D3="",D3=0),"",E3/D3)
A4: ='EVM - Valor Agregado'!B4 | B4: ='EVM - Valor Agregado'!A4 | C4: ='EVM - Valor Agregado'!E4 | D4: =IF('EVM - Valor Agregado'!G4="","",'EVM - Valor Agregado'!G4) | E4: =IF('EVM - Valor Agregado'!G4="","",'EVM - Valor Agregado'!H4) | F4: =E4 | G4: =IF(E4="","",E4/C4) | H4: =IF(G4="","",AVERAGE($G$2:G4)) | I4: =IF(OR(D4="",D4=0),"",E4/D4)
A5: ='EVM - Valor Agregado'!B5 | B5: ='EVM - Valor Agregado'!A5 | C5: ='EVM - Valor Agregado'!E5 | D5: =IF('EVM - Valor Agregado'!G5="","",'EVM - Valor Agregado'!G5) | E5: =IF('EVM - Valor Agregado'!G5="","",'EVM - Valor Agregado'!H5) | F5: =E5 | G5: =IF(E5="","",E5/C5) | H5: =IF(G5="","",AVERAGE($G$2:G5)) | I5: =IF(OR(D5="",D5=0),"",E5/D5)
A6: ='EVM - Valor Agregado'!B6 | B6: ='EVM - Valor Agregado'!A6 | C6: ='EVM - Valor Agregado'!E6 | D6: =IF('EVM - Valor Agregado'!G6="","",'EVM - Valor Agregado'!G6) | E6: =IF('EVM - Valor Agregado'!G6="","",'EVM - Valor Agregado'!H6) | F6: =E6 | G6: =IF(E6="","",E6/C6) | H6: =IF(G6="","",AVERAGE($G$2:G6)) | I6: =IF(OR(D6="",D6=0),"",E6/D6)
A7: ='EVM - Valor Agregado'!B7 | B7: ='EVM - Valor Agregado'!A7 | C7: ='EVM - Valor Agregado'!E7 | D7: =IF('EVM - Valor Agregado'!G7="","",'EVM - Valor Agregado'!G7) | E7: =IF('EVM - Valor Agregado'!G7="","",'EVM - Valor Agregado'!H7) | F7: =E7 | G7: =IF(E7="","",E7/C7) | H7: =IF(G7="","",AVERAGE($G$2:G7)) | I7: =IF(OR(D7="",D7=0),"",E7/D7)
A8: ='EVM - Valor Agregado'!B8 | B8: ='EVM - Valor Agregado'!A8 | C8: ='EVM - Valor Agregado'!E8 | D8: =IF('EVM - Valor Agregado'!G8="","",'EVM - Valor Agregado'!G8) | E8: =IF('EVM - Valor Agregado'!G8="","",'EVM - Valor Agregado'!H8) | F8: =E8 | G8: =IF(E8="","",E8/C8) | H8: =IF(G8="","",AVERAGE($G$2:G8)) | I8: =IF(OR(D8="",D8=0),"",E8/D8)
A9: ='EVM - Valor Agregado'!B9 | B9: ='EVM - Valor Agregado'!A9 | C9: ='EVM - Valor Agregado'!E9 | D9: =IF('EVM - Valor Agregado'!G9="","",'EVM - Valor Agregado'!G9) | E9: =IF('EVM - Valor Agregado'!G9="","",'EVM - Valor Agregado'!H9) | F9: =E9 | G9: =IF(E9="","",E9/C9) | H9: =IF(G9="","",AVERAGE($G$2:G9)) | I9: =IF(OR(D9="",D9=0),"",E9/D9)
A10: ='EVM - Valor Agregado'!B10 | B10: ='EVM - Valor Agregado'!A10 | C10: ='EVM - Valor Agregado'!E10 | D10: =IF('EVM - Valor Agregado'!G10="","",'EVM - Valor Agregado'!G10) | E10: =IF('EVM - Valor Agregado'!G10="","",'EVM - Valor Agregado'!H10) | F10: =E10 | G10: =IF(E10="","",E10/C10) | H10: =IF(G10="","",AVERAGE($G$2:G10)) | I10: =IF(OR(D10="",D10=0),"",E10/D10)
A11: ='EVM - Valor Agregado'!B11 | B11: ='EVM - Valor Agregado'!A11 | C11: ='EVM - Valor Agregado'!E11 | D11: =IF('EVM - Valor Agregado'!G11="","",'EVM - Valor Agregado'!G11) | E11: =IF('EVM - Valor Agregado'!G11="","",'EVM - Valor Agregado'!H11) | F11: =E11 | G11: =IF(E11="","",E11/C11) | H11: =IF(G11="","",AVERAGE($G$2:G11)) | I11: =IF(OR(D11="",D11=0),"",E11/D11)
A12: ='EVM - Valor Agregado'!B12 | B12: ='EVM - Valor Agregado'!A12 | C12: ='EVM - Valor Agregado'!E12 | D12: =IF('EVM - Valor Agregado'!G12="","",'EVM - Valor Agregado'!G12) | E12: =IF('EVM - Valor Agregado'!G12="","",'EVM - Valor Agregado'!H12) | F12: =E12 | G12: =IF(E12="","",E12/C12) | H12: =IF(G12="","",AVERAGE($G$2:G12)) | I12: =IF(OR(D12="",D12=0),"",E12/D12)
A13: ='EVM - Valor Agregado'!B13 | B13: ='EVM - Valor Agregado'!A13 | C13: ='EVM - Valor Agregado'!E13 | D13: =IF('EVM - Valor Agregado'!G13="","",'EVM - Valor Agregado'!G13) | E13: =IF('EVM - Valor Agregado'!G13="","",'EVM - Valor Agregado'!H13) | F13: =E13 | G13: =IF(E13="","",E13/C13) | H13: =IF(G13="","",AVERAGE($G$2:G13)) | I13: =IF(OR(D13="",D13=0),"",E13/D13)

Sheet EVM - Índices e Burndown
A1: Sprint | B1: Release | C1: SPI | D1: CPI | E1: Referência (1,0) | F1: PRP | G1: Pontos restantes | H1: Restante ideal
A2: ='EVM - Valor Agregado'!B2 | B2: ='EVM - Valor Agregado'!A2 | C2: ='EVM - Valor Agregado'!Y2 | D2: ='EVM - Valor Agregado'!X2 | E2: 1 | F2: ='EVM - Valor Agregado'!J2 | G2: =IF('EVM - Valor Agregado'!J2="","",'EVM - Valor Agregado'!J2-'EVM - Valor Agregado'!K2) | H2: =IF('EVM - Valor Agregado'!J2="","",'EVM - Valor Agregado'!J2*(1-'EVM - Valor Agregado'!M2))
A3: ='EVM - Valor Agregado'!B3 | B3: ='EVM - Valor Agregado'!A3 | C3: ='EVM - Valor Agregado'!Y3 | D3: ='EVM - Valor Agregado'!X3 | E3: 1 | F3: ='EVM - Valor Agregado'!J3 | G3: =IF('EVM - Valor Agregado'!J3="","",'EVM - Valor Agregado'!J3-'EVM - Valor Agregado'!K3) | H3: =IF('EVM - Valor Agregado'!J3="","",'EVM - Valor Agregado'!J3*(1-'EVM - Valor Agregado'!M3))
A4: ='EVM - Valor Agregado'!B4 | B4: ='EVM - Valor Agregado'!A4 | C4: ='EVM - Valor Agregado'!Y4 | D4: ='EVM - Valor Agregado'!X4 | E4: 1 | F4: ='EVM - Valor Agregado'!J4 | G4: =IF('EVM - Valor Agregado'!J4="","",'EVM - Valor Agregado'!J4-'EVM - Valor Agregado'!K4) | H4: =IF('EVM - Valor Agregado'!J4="","",'EVM - Valor Agregado'!J4*(1-'EVM - Valor Agregado'!M4))
A5: ='EVM - Valor Agregado'!B5 | B5: ='EVM - Valor Agregado'!A5 | C5: ='EVM - Valor Agregado'!Y5 | D5: ='EVM - Valor Agregado'!X5 | E5: 1 | F5: ='EVM - Valor Agregado'!J5 | G5: =IF('EVM - Valor Agregado'!J5="","",'EVM - Valor Agregado'!J5-'EVM - Valor Agregado'!K5) | H5: =IF('EVM - Valor Agregado'!J5="","",'EVM - Valor Agregado'!J5*(1-'EVM - Valor Agregado'!M5))
A6: ='EVM - Valor Agregado'!B6 | B6: ='EVM - Valor Agregado'!A6 | C6: ='EVM - Valor Agregado'!Y6 | D6: ='EVM - Valor Agregado'!X6 | E6: 1 | F6: ='EVM - Valor Agregado'!J6 | G6: =IF('EVM - Valor Agregado'!J6="","",'EVM - Valor Agregado'!J6-'EVM - Valor Agregado'!K6) | H6: =IF('EVM - Valor Agregado'!J6="","",'EVM - Valor Agregado'!J6*(1-'EVM - Valor Agregado'!M6))
A7: ='EVM - Valor Agregado'!B7 | B7: ='EVM - Valor Agregado'!A7 | C7: ='EVM - Valor Agregado'!Y7 | D7: ='EVM - Valor Agregado'!X7 | E7: 1 | F7: ='EVM - Valor Agregado'!J7 | G7: =IF('EVM - Valor Agregado'!J7="","",'EVM - Valor Agregado'!J7-'EVM - Valor Agregado'!K7) | H7: =IF('EVM - Valor Agregado'!J7="","",'EVM - Valor Agregado'!J7*(1-'EVM - Valor Agregado'!M7))
A8: ='EVM - Valor Agregado'!B8 | B8: ='EVM - Valor Agregado'!A8 | C8: ='EVM - Valor Agregado'!Y8 | D8: ='EVM - Valor Agregado'!X8 | E8: 1 | F8: ='EVM - Valor Agregado'!J8 | G8: =IF('EVM - Valor Agregado'!J8="","",'EVM - Valor Agregado'!J8-'EVM - Valor Agregado'!K8) | H8: =IF('EVM - Valor Agregado'!J8="","",'EVM - Valor Agregado'!J8*(1-'EVM - Valor Agregado'!M8))
A9: ='EVM - Valor Agregado'!B9 | B9: ='EVM - Valor Agregado'!A9 | C9: ='EVM - Valor Agregado'!Y9 | D9: ='EVM - Valor Agregado'!X9 | E9: 1 | F9: ='EVM - Valor Agregado'!J9 | G9: =IF('EVM - Valor Agregado'!J9="","",'EVM - Valor Agregado'!J9-'EVM - Valor Agregado'!K9) | H9: =IF('EVM - Valor Agregado'!J9="","",'EVM - Valor Agregado'!J9*(1-'EVM - Valor Agregado'!M9))
A10: ='EVM - Valor Agregado'!B10 | B10: ='EVM - Valor Agregado'!A10 | C10: ='EVM - Valor Agregado'!Y10 | D10: ='EVM - Valor Agregado'!X10 | E10: 1 | F10: ='EVM - Valor Agregado'!J10 | G10: =IF('EVM - Valor Agregado'!J10="","",'EVM - Valor Agregado'!J10-'EVM - Valor Agregado'!K10) | H10: =IF('EVM - Valor Agregado'!J10="","",'EVM - Valor Agregado'!J10*(1-'EVM - Valor Agregado'!M10))
A11: ='EVM - Valor Agregado'!B11 | B11: ='EVM - Valor Agregado'!A11 | C11: ='EVM - Valor Agregado'!Y11 | D11: ='EVM - Valor Agregado'!X11 | E11: 1 | F11: ='EVM - Valor Agregado'!J11 | G11: =IF('EVM - Valor Agregado'!J11="","",'EVM - Valor Agregado'!J11-'EVM - Valor Agregado'!K11) | H11: =IF('EVM - Valor Agregado'!J11="","",'EVM - Valor Agregado'!J11*(1-'EVM - Valor Agregado'!M11))
A12: ='EVM - Valor Agregado'!B12 | B12: ='EVM - Valor Agregado'!A12 | C12: ='EVM - Valor Agregado'!Y12 | D12: ='EVM - Valor Agregado'!X12 | E12: 1 | F12: ='EVM - Valor Agregado'!J12 | G12: =IF('EVM - Valor Agregado'!J12="","",'EVM - Valor Agregado'!J12-'EVM - Valor Agregado'!K12) | H12: =IF('EVM - Valor Agregado'!J12="","",'EVM - Valor Agregado'!J12*(1-'EVM - Valor Agregado'!M12))
A13: ='EVM - Valor Agregado'!B13 | B13: ='EVM - Valor Agregado'!A13 | C13: ='EVM - Valor Agregado'!Y13 | D13: ='EVM - Valor Agregado'!X13 | E13: 1 | F13: ='EVM - Valor Agregado'!J13 | G13: =IF('EVM - Valor Agregado'!J13="","",'EVM - Valor Agregado'!J13-'EVM - Valor Agregado'!K13) | H13: =IF('EVM - Valor Agregado'!J13="","",'EVM - Valor Agregado'!J13*(1-'EVM - Valor Agregado'!M13))
