Workbook

Sheet Leia-me
A1: MeasureSoftGram 2026.2 · Riscos e Decisões
A2: Plano de riscos no formato de 2026.1 (escalas 1 a 5, EAR, causa, consequência, prevenção e contingência), com o monitoramento por sprint que alimenta o dashboard. Passe o mouse nos títulos das colunas para ver o que cada uma significa.
A4: Cores
A5: Amarelo | B5: Dado preenchido pelo time.
A6: Azul-claro | B6: Calculado. Não digitar por cima.
A8: Abas
A9: Escalas | B9: Escala de probabilidade, de impacto e faixas de exposição.
A10: Riscos | B10: Identificação e plano de resposta de cada risco. P, I e exposição atuais vêm da última avaliação no Monitoramento.
A11: Monitoramento | B11: Uma linha por risco por sprint avaliada. É o histórico que mostra se o risco está subindo ou caindo.
A12: Matriz | B12: Matriz 5×5 calculada a partir das avaliações atuais.
A13: Decisões | B13: Decisões tomadas a partir do dashboard: contexto, decisão, evidência, critério de sucesso e resultado. A disciplina pede ≥ 3 na R2 e ≥ 5 na R3.
A15: Rotina
A16: Toda planning | B16: Reavaliar os riscos ativos: acrescentar uma linha por risco no Monitoramento com a sprint, P e I. Risco novo: criar na aba Riscos e avaliar no Monitoramento.
A17: Decisão nova | B17: Registrar na aba Decisões e citar o gráfico do dashboard que a motivou.
A19: Origem dos riscos
A20: 27/09/2026 | B20: R01 a R14 identificados a partir do diagnóstico do ecossistema (docs/diagnostico), das métricas do SonarCloud e da CI (Analytics/data) e do quadro do Zenhub. Responsável = quem está na issue que trata o risco. Proposta para o time validar.
A22: Dashboard
A23: Publicar | B23: Arquivo → Compartilhar → Publicar na Web → CSV das abas Riscos, Monitoramento e Decisões; colar os links em Analytics/config.py.

Sheet Escalas
A1: Escalas usadas no plano de riscos (mesmas de 2026.1)
A3: Probabilidade
A4: Nível | B4: Descrição | C4: Chance de ocorrer
A5: 1 | B5: Muito baixa | C5: 0 a 19%
A6: 2 | B6: Baixa | C6: 20 a 39%
A7: 3 | B7: Média | C7: 40 a 59%
A8: 4 | B8: Alta | C8: 60 a 79%
A9: 5 | B9: Muito alta | C9: 80 a 100%
A11: Impacto
A12: Nível | B12: Descrição | C12: Efeito no projeto
A13: 1 | B13: Muito baixo | C13: Quase imperceptível; sem efeito em prazo, custo ou qualidade
A14: 2 | B14: Baixo | C14: Atraso ou retrabalho pequeno, absorvido na própria sprint
A15: 3 | B15: Médio | C15: Afeta uma entrega da release; exige replanejar tasks
A16: 4 | B16: Alto | C16: Compromete um critério da release ou a nota de qualidade
A17: 5 | B17: Muito alto | C17: Impede a entrega da release ou expõe dado de usuário
A19: Exposição = Probabilidade × Impacto
A20: Faixa | B20: Nível | C20: O que fazer
A21: 1 a 5 | B21: Baixo | C21: Aceitar e acompanhar
A22: 6 a 12 | B22: Médio | C22: Plano de resposta com responsável
A23: 15 a 25 | B23: Elevado | C23: Resposta imediata; revisar em toda sprint

Sheet Riscos
A1: ID | B1: Categoria (EAR) | C1: Risco | D1: Causa | E1: Consequência | F1: Gatilho | G1: Resposta | H1: Ação preventiva | I1: Contingência | J1: Responsável | K1: Status | L1: Identificado em | M1: Última sprint avaliada | N1: Probabilidade atual | O1: Impacto atual | P1: Exposição atual | Q1: Nível
A2: R01 | B2: Técnico | C2: Motor de cálculo publicado não corresponde ao código versionado | D2: Core versionado em 1.5.3, PyPI com msgram-core 1.5.4 publicado de código fora do repositório; Service usa 1.4.9 | E2: Nota de qualidade não reproduzível; CLI e Web dão resultados diferentes para o mesmo projeto | F2: Teste de regressão entre CLI e Service com notas diferentes | G2: Mitigar | H2: TASK05.03 (DOC#50): padronizar msgram-core 1.5.4 no Service e na CLI (PRs Service#19 e CLI#4) | I2: Congelar a versão do Core usada na homologação e documentar a divergência na R1 | J2: Nathan Benigno Ponce de Abreu | K2: Aberto | L2: 46292 | M2: =IF($A2="","",_xlfn.MAXIFS(Monitoramento!$B$2:$B$200,Monitoramento!$A$2:$A$200,$A2)) | N2: =IF(OR($A2="",M2=0),"",SUMIFS(Monitoramento!$D$2:$D$200,Monitoramento!$A$2:$A$200,$A2,Monitoramento!$B$2:$B$200,M2)) | O2: =IF(OR($A2="",M2=0),"",SUMIFS(Monitoramento!$E$2:$E$200,Monitoramento!$A$2:$A$200,$A2,Monitoramento!$B$2:$B$200,M2)) | P2: =IF(N2="","",N2*O2) | Q2: =IF(P2="","",IF(P2>=15,"Elevado",IF(P2>=6,"Médio","Baixo")))
A3: R02 | B3: Técnico | C3: Endpoint público expõe e-mail de todos os usuários | D3: GET /users/ do Service sem autenticação (diagnóstico, gravidade Crítico) | E3: Vazamento de dado pessoal (LGPD) no ambiente publicado | F3: Endpoint respondendo sem token em homologação | G3: Mitigar | H3: BUG05.01 (DOC#52): corrigir falhas de segurança MSG-03, MSG-12 e MSG-13; Django já atualizado para 5.2 LTS (Service#3) | I3: Desativar a rota em homologação até a correção | J3: Marcos Antonio Teles de Castilhos | K3: Aberto | L3: 46292 | M3: =IF($A3="","",_xlfn.MAXIFS(Monitoramento!$B$2:$B$200,Monitoramento!$A$2:$A$200,$A3)) | N3: =IF(OR($A3="",M3=0),"",SUMIFS(Monitoramento!$D$2:$D$200,Monitoramento!$A$2:$A$200,$A3,Monitoramento!$B$2:$B$200,M3)) | O3: =IF(OR($A3="",M3=0),"",SUMIFS(Monitoramento!$E$2:$E$200,Monitoramento!$A$2:$A$200,$A3,Monitoramento!$B$2:$B$200,M3)) | P3: =IF(N3="","",N3*O3) | Q3: =IF(P3="","",IF(P3>=15,"Elevado",IF(P3>=6,"Médio","Baixo")))
A4: R03 | B4: Técnico | C4: Nenhum portão de qualidade bloqueante nos repositórios | D4: CI não é exigida antes do merge e o Service não define fail_under de cobertura | E4: Regressões e queda de cobertura entram na develop sem aviso | F4: PR mergeado com CI falhando ou sem rodar | G4: Mitigar | H4: DOC#74: governança de branches, portões de CI e gestão de secrets nos repositórios centrais | I4: Revisão manual obrigatória da CI no template de PR | J4: Luciano Freitas | K4: Aberto | L4: 46292 | M4: =IF($A4="","",_xlfn.MAXIFS(Monitoramento!$B$2:$B$200,Monitoramento!$A$2:$A$200,$A4)) | N4: =IF(OR($A4="",M4=0),"",SUMIFS(Monitoramento!$D$2:$D$200,Monitoramento!$A$2:$A$200,$A4,Monitoramento!$B$2:$B$200,M4)) | O4: =IF(OR($A4="",M4=0),"",SUMIFS(Monitoramento!$E$2:$E$200,Monitoramento!$A$2:$A$200,$A4,Monitoramento!$B$2:$B$200,M4)) | P4: =IF(N4="","",N4*O4) | Q4: =IF(P4="","",IF(P4>=15,"Elevado",IF(P4>=6,"Médio","Baixo")))
A5: R04 | B5: Organizacional | C5: Coordenação técnica entre squads que atravessam repositórios | D5: Fatias verticais tocam vários repositórios (ex.: dívida técnica em Action, Parser, CLI e Front) | E5: Tasks bloqueadas esperando outro repositório; retrabalho de integração | F5: Issue bloqueada por outra de outro repositório por mais de uma sprint | G5: Mitigar | H5: Modelo de squads por release (docs/planejamento/squads) e dependências registradas no Zenhub (blocking) | I5: Sessão de integração na planning de segunda | J5: Milena Fernandes Rocha | K5: Aberto | L5: 46292 | M5: =IF($A5="","",_xlfn.MAXIFS(Monitoramento!$B$2:$B$200,Monitoramento!$A$2:$A$200,$A5)) | N5: =IF(OR($A5="",M5=0),"",SUMIFS(Monitoramento!$D$2:$D$200,Monitoramento!$A$2:$A$200,$A5,Monitoramento!$B$2:$B$200,M5)) | O5: =IF(OR($A5="",M5=0),"",SUMIFS(Monitoramento!$E$2:$E$200,Monitoramento!$A$2:$A$200,$A5,Monitoramento!$B$2:$B$200,M5)) | P5: =IF(N5="","",N5*O5) | Q5: =IF(P5="","",IF(P5>=15,"Elevado",IF(P5>=6,"Médio","Baixo")))
A6: R05 | B6: Gerencial | C6: Objetivo do semestre ainda não fechado com o PO | D6: Primeira reunião com o PO foi expositiva; Visão do Produto ainda em andamento (DOC#18) | E6: Backlog priorizado sem validação; risco de entregar o que o PO não espera | F6: US voltando de 'Aguardando validação do PO (DoR)' | G6: Mitigar | H6: Pauta preparada para a reunião semanal com o PO; validar Visão do Produto e Canvas MVP | I6: Escalar ao professor se não houver validação até a R2 | J6: Guilherme Storch | K6: Aberto | L6: 46292 | M6: =IF($A6="","",_xlfn.MAXIFS(Monitoramento!$B$2:$B$200,Monitoramento!$A$2:$A$200,$A6)) | N6: =IF(OR($A6="",M6=0),"",SUMIFS(Monitoramento!$D$2:$D$200,Monitoramento!$A$2:$A$200,$A6,Monitoramento!$B$2:$B$200,M6)) | O6: =IF(OR($A6="",M6=0),"",SUMIFS(Monitoramento!$E$2:$E$200,Monitoramento!$A$2:$A$200,$A6,Monitoramento!$B$2:$B$200,M6)) | P6: =IF(N6="","",N6*O6) | Q6: =IF(P6="","",IF(P6>=15,"Elevado",IF(P6>=6,"Médio","Baixo")))
A7: R06 | B7: Organizacional | C7: Desbalanceamento de contribuições num time de 20 pessoas | D7: Time grande com níveis de conhecimento diferentes (aba Habilidades); várias issues sem responsável | E7: Concentração de carga e avaliação individual prejudicada na R2 (contribuições equilibradas) | F7: Integrante sem horas ou sem issue atribuída na sprint | G7: Aceitar | H7: Acompanhar horas por integrante (aba Horas) e issues por pessoa no dashboard | I7: Redistribuir tasks na planning seguinte | J7: Milena Fernandes Rocha | K7: Em monitoramento | L7: 46292 | M7: =IF($A7="","",_xlfn.MAXIFS(Monitoramento!$B$2:$B$200,Monitoramento!$A$2:$A$200,$A7)) | N7: =IF(OR($A7="",M7=0),"",SUMIFS(Monitoramento!$D$2:$D$200,Monitoramento!$A$2:$A$200,$A7,Monitoramento!$B$2:$B$200,M7)) | O7: =IF(OR($A7="",M7=0),"",SUMIFS(Monitoramento!$E$2:$E$200,Monitoramento!$A$2:$A$200,$A7,Monitoramento!$B$2:$B$200,M7)) | P7: =IF(N7="","",N7*O7) | Q7: =IF(P7="","",IF(P7>=15,"Elevado",IF(P7>=6,"Médio","Baixo")))
A8: R07 | B8: Técnico | C8: Métricas de repositórios publicadas em repos de semestres anteriores | D8: metrics.yml de alguns repositórios ainda publica no repositório central (MeasureSoftGram-Core aparece junto do 2026.2-Core) | E8: Dashboard com dado misturado ou faltando | F8: Arquivo de métricas com prefixo sem '2026.2-' em Analytics/data | G8: Mitigar | H8: DOC#14 (organização dos repositórios): apontar o metrics.yml de todos para o docs-eps de 2026.2 | I8: Filtrar no dashboard só repositórios 2026.2 | J8: Milena Fernandes Rocha | K8: Aberto | L8: 46292 | M8: =IF($A8="","",_xlfn.MAXIFS(Monitoramento!$B$2:$B$200,Monitoramento!$A$2:$A$200,$A8)) | N8: =IF(OR($A8="",M8=0),"",SUMIFS(Monitoramento!$D$2:$D$200,Monitoramento!$A$2:$A$200,$A8,Monitoramento!$B$2:$B$200,M8)) | O8: =IF(OR($A8="",M8=0),"",SUMIFS(Monitoramento!$E$2:$E$200,Monitoramento!$A$2:$A$200,$A8,Monitoramento!$B$2:$B$200,M8)) | P8: =IF(N8="","",N8*O8) | Q8: =IF(P8="","",IF(P8>=15,"Elevado",IF(P8>=6,"Médio","Baixo")))
A9: R08 | B9: Técnico | C9: Cobertura abaixo da meta de 85% em Front (80,4%), Service (82,4%) e Action (82,7%) | D9: Suítes herdadas sem manutenção desde 2024 e sem portão de cobertura | E9: Critério da R1 (cobertura ≥ 85%) não atendido em 3 de 7 repositórios | F9: Cobertura abaixo de 85% na última coleta do SonarCloud | G9: Mitigar | H9: TASK03.02 (DOC#57): saneamento do backlog técnico; testes nos componentes com menor cobertura (painel do dashboard) | I9: Priorizar testes do Front e do Service na sprint 4 | J9: Antônio José Magalhães Leão Júnior | K9: Aberto | L9: 46292 | M9: =IF($A9="","",_xlfn.MAXIFS(Monitoramento!$B$2:$B$200,Monitoramento!$A$2:$A$200,$A9)) | N9: =IF(OR($A9="",M9=0),"",SUMIFS(Monitoramento!$D$2:$D$200,Monitoramento!$A$2:$A$200,$A9,Monitoramento!$B$2:$B$200,M9)) | O9: =IF(OR($A9="",M9=0),"",SUMIFS(Monitoramento!$E$2:$E$200,Monitoramento!$A$2:$A$200,$A9,Monitoramento!$B$2:$B$200,M9)) | P9: =IF(N9="","",N9*O9) | Q9: =IF(P9="","",IF(P9>=15,"Elevado",IF(P9>=6,"Médio","Baixo")))
A10: R09 | B10: Técnico | C10: Taxa de falha da CI em 35% (65 de 188 execuções), com Service em 45% e Action em 41% | D10: Workflows antigos (actions descontinuadas) e metrics.yml falhando no Front e no Service | E10: Time aprende a ignorar a CI; métricas deixam de ser coletadas | F10: Taxa de falha acima de 20% no dashboard | G10: Mitigar | H10: TASK03.01 (DOC#73) e DOC#74: atualizar workflows e corrigir o metrics.yml | I10: Rodar o metrics.yml manualmente (workflow_dispatch) antes de cada release | J10: Luciano Freitas | K10: Aberto | L10: 46292 | M10: =IF($A10="","",_xlfn.MAXIFS(Monitoramento!$B$2:$B$200,Monitoramento!$A$2:$A$200,$A10)) | N10: =IF(OR($A10="",M10=0),"",SUMIFS(Monitoramento!$D$2:$D$200,Monitoramento!$A$2:$A$200,$A10,Monitoramento!$B$2:$B$200,M10)) | O10: =IF(OR($A10="",M10=0),"",SUMIFS(Monitoramento!$E$2:$E$200,Monitoramento!$A$2:$A$200,$A10,Monitoramento!$B$2:$B$200,M10)) | P10: =IF(N10="","",N10*O10) | Q10: =IF(P10="","",IF(P10>=15,"Elevado",IF(P10>=6,"Médio","Baixo")))
A11: R10 | B11: Gerencial | C11: Sequenciador da Lean Inception atrasado frente ao cronograma | D11: Sequenciador previsto para 24/08 não fechou | E11: R1 sem linha de base de escopo (PRP); fatias verticais não decompostas na EAP | F11: Planning da release sem US priorizadas | G11: Mitigar | H11: EAP com pacotes de planejamento; linha de base da R2 congelada na planning de 28/09 | I11: Usar o PRP reconstituído do Zenhub na R1 e declarar no dashboard | J11: Guilherme Storch | K11: Materializado | L11: 46292 | M11: =IF($A11="","",_xlfn.MAXIFS(Monitoramento!$B$2:$B$200,Monitoramento!$A$2:$A$200,$A11)) | N11: =IF(OR($A11="",M11=0),"",SUMIFS(Monitoramento!$D$2:$D$200,Monitoramento!$A$2:$A$200,$A11,Monitoramento!$B$2:$B$200,M11)) | O11: =IF(OR($A11="",M11=0),"",SUMIFS(Monitoramento!$E$2:$E$200,Monitoramento!$A$2:$A$200,$A11,Monitoramento!$B$2:$B$200,M11)) | P11: =IF(N11="","",N11*O11) | Q11: =IF(P11="","",IF(P11>=15,"Elevado",IF(P11>=6,"Médio","Baixo")))
A12: R11 | B12: Técnico | C12: AI e Plugin sem projeto válido no SonarCloud | D12: A coleta do metrics.yml grava erro de component key para AI e Plugin | E12: Qualidade de 2 dos 9 módulos fica invisível no dashboard e na avaliação | F12: Arquivo de coleta com 'Component key' em vez de métricas | G12: Mitigar | H12: Criar os projetos no SonarCloud da organização e corrigir a chave no metrics.yml | I12: Declarar no dashboard os módulos sem métrica | J12: Antônio José Magalhães Leão Júnior | K12: Aberto | L12: 46292 | M12: =IF($A12="","",_xlfn.MAXIFS(Monitoramento!$B$2:$B$200,Monitoramento!$A$2:$A$200,$A12)) | N12: =IF(OR($A12="",M12=0),"",SUMIFS(Monitoramento!$D$2:$D$200,Monitoramento!$A$2:$A$200,$A12,Monitoramento!$B$2:$B$200,M12)) | O12: =IF(OR($A12="",M12=0),"",SUMIFS(Monitoramento!$E$2:$E$200,Monitoramento!$A$2:$A$200,$A12,Monitoramento!$B$2:$B$200,M12)) | P12: =IF(N12="","",N12*O12) | Q12: =IF(P12="","",IF(P12>=15,"Elevado",IF(P12>=6,"Médio","Baixo")))
A13: R12 | B13: Técnico | C13: Rating de segurança E no Plugin e C no Service (SonarCloud) | D13: Vulnerabilidades apontadas pelo SonarCloud na última coleta (security_rating 5 no Plugin, 3 no Service) | E13: Produto publicado com vulnerabilidade conhecida | F13: security_rating acima de 1 (A) em qualquer repositório | G13: Mitigar | H13: Revisar os security hotspots do Plugin e do Service e corrigir as vulnerabilidades | I13: Não publicar nova versão do Plugin até o rating voltar para A | J13: Nathan Benigno Ponce de Abreu | K13: Aberto | L13: 46292 | M13: =IF($A13="","",_xlfn.MAXIFS(Monitoramento!$B$2:$B$200,Monitoramento!$A$2:$A$200,$A13)) | N13: =IF(OR($A13="",M13=0),"",SUMIFS(Monitoramento!$D$2:$D$200,Monitoramento!$A$2:$A$200,$A13,Monitoramento!$B$2:$B$200,M13)) | O13: =IF(OR($A13="",M13=0),"",SUMIFS(Monitoramento!$E$2:$E$200,Monitoramento!$A$2:$A$200,$A13,Monitoramento!$B$2:$B$200,M13)) | P13: =IF(N13="","",N13*O13) | Q13: =IF(P13="","",IF(P13>=15,"Elevado",IF(P13>=6,"Médio","Baixo")))
... A15: R14 | B15: Gerencial | C15: Horas reais não registradas pela equipe | D15: Registro de horas criado só em 27/09; sprints 1 a 3 sem dado | E15: Sem custo real (AC) não há CPI nem EAC; exigência da disciplina não atendida | F15: Integrantes sem horas na aba Horas após a planning | G15: Mitigar | H15: Lançar horas toda segunda na planning (decisão D3) | I15: Declarar o período sem dado no dashboard; não estimar retroativamente | J15: Daniel Ferreira Santos Rabelo | K15: Aberto | L15: 46292 | M15: =IF($A15="","",_xlfn.MAXIFS(Monitoramento!$B$2:$B$200,Monitoramento!$A$2:$A$200,$A15)) | N15: =IF(OR($A15="",M15=0),"",SUMIFS(Monitoramento!$D$2:$D$200,Monitoramento!$A$2:$A$200,$A15,Monitoramento!$B$2:$B$200,M15)) | O15: =IF(OR($A15="",M15=0),"",SUMIFS(Monitoramento!$E$2:$E$200,Monitoramento!$A$2:$A$200,$A15,Monitoramento!$B$2:$B$200,M15)) | P15: =IF(N15="","",N15*O15) | Q15: =IF(P15="","",IF(P15>=15,"Elevado",IF(P15>=6,"Médio","Baixo")))
M16: =IF($A16="","",_xlfn.MAXIFS(Monitoramento!$B$2:$B$200,Monitoramento!$A$2:$A$200,$A16)) | N16: =IF(OR($A16="",M16=0),"",SUMIFS(Monitoramento!$D$2:$D$200,Monitoramento!$A$2:$A$200,$A16,Monitoramento!$B$2:$B$200,M16)) | O16: =IF(OR($A16="",M16=0),"",SUMIFS(Monitoramento!$E$2:$E$200,Monitoramento!$A$2:$A$200,$A16,Monitoramento!$B$2:$B$200,M16)) | P16: =IF(N16="","",N16*O16) | Q16: =IF(P16="","",IF(P16>=15,"Elevado",IF(P16>=6,"Médio","Baixo")))
M17: =IF($A17="","",_xlfn.MAXIFS(Monitoramento!$B$2:$B$200,Monitoramento!$A$2:$A$200,$A17)) | N17: =IF(OR($A17="",M17=0),"",SUMIFS(Monitoramento!$D$2:$D$200,Monitoramento!$A$2:$A$200,$A17,Monitoramento!$B$2:$B$200,M17)) | O17: =IF(OR($A17="",M17=0),"",SUMIFS(Monitoramento!$E$2:$E$200,Monitoramento!$A$2:$A$200,$A17,Monitoramento!$B$2:$B$200,M17)) | P17: =IF(N17="","",N17*O17) | Q17: =IF(P17="","",IF(P17>=15,"Elevado",IF(P17>=6,"Médio","Baixo")))
M18: =IF($A18="","",_xlfn.MAXIFS(Monitoramento!$B$2:$B$200,Monitoramento!$A$2:$A$200,$A18)) | N18: =IF(OR($A18="",M18=0),"",SUMIFS(Monitoramento!$D$2:$D$200,Monitoramento!$A$2:$A$200,$A18,Monitoramento!$B$2:$B$200,M18)) | O18: =IF(OR($A18="",M18=0),"",SUMIFS(Monitoramento!$E$2:$E$200,Monitoramento!$A$2:$A$200,$A18,Monitoramento!$B$2:$B$200,M18)) | P18: =IF(N18="","",N18*O18) | Q18: =IF(P18="","",IF(P18>=15,"Elevado",IF(P18>=6,"Médio","Baixo")))
M19: =IF($A19="","",_xlfn.MAXIFS(Monitoramento!$B$2:$B$200,Monitoramento!$A$2:$A$200,$A19)) | N19: =IF(OR($A19="",M19=0),"",SUMIFS(Monitoramento!$D$2:$D$200,Monitoramento!$A$2:$A$200,$A19,Monitoramento!$B$2:$B$200,M19)) | O19: =IF(OR($A19="",M19=0),"",SUMIFS(Monitoramento!$E$2:$E$200,Monitoramento!$A$2:$A$200,$A19,Monitoramento!$B$2:$B$200,M19)) | P19: =IF(N19="","",N19*O19) | Q19: =IF(P19="","",IF(P19>=15,"Elevado",IF(P19>=6,"Médio","Baixo")))
M20: =IF($A20="","",_xlfn.MAXIFS(Monitoramento!$B$2:$B$200,Monitoramento!$A$2:$A$200,$A20)) | N20: =IF(OR($A20="",M20=0),"",SUMIFS(Monitoramento!$D$2:$D$200,Monitoramento!$A$2:$A$200,$A20,Monitoramento!$B$2:$B$200,M20)) | O20: =IF(OR($A20="",M20=0),"",SUMIFS(Monitoramento!$E$2:$E$200,Monitoramento!$A$2:$A$200,$A20,Monitoramento!$B$2:$B$200,M20)) | P20: =IF(N20="","",N20*O20) | Q20: =IF(P20="","",IF(P20>=15,"Elevado",IF(P20>=6,"Médio","Baixo")))
M21: =IF($A21="","",_xlfn.MAXIFS(Monitoramento!$B$2:$B$200,Monitoramento!$A$2:$A$200,$A21)) | N21: =IF(OR($A21="",M21=0),"",SUMIFS(Monitoramento!$D$2:$D$200,Monitoramento!$A$2:$A$200,$A21,Monitoramento!$B$2:$B$200,M21)) | O21: =IF(OR($A21="",M21=0),"",SUMIFS(Monitoramento!$E$2:$E$200,Monitoramento!$A$2:$A$200,$A21,Monitoramento!$B$2:$B$200,M21)) | P21: =IF(N21="","",N21*O21) | Q21: =IF(P21="","",IF(P21>=15,"Elevado",IF(P21>=6,"Médio","Baixo")))
M22: =IF($A22="","",_xlfn.MAXIFS(Monitoramento!$B$2:$B$200,Monitoramento!$A$2:$A$200,$A22)) | N22: =IF(OR($A22="",M22=0),"",SUMIFS(Monitoramento!$D$2:$D$200,Monitoramento!$A$2:$A$200,$A22,Monitoramento!$B$2:$B$200,M22)) | O22: =IF(OR($A22="",M22=0),"",SUMIFS(Monitoramento!$E$2:$E$200,Monitoramento!$A$2:$A$200,$A22,Monitoramento!$B$2:$B$200,M22)) | P22: =IF(N22="","",N22*O22) | Q22: =IF(P22="","",IF(P22>=15,"Elevado",IF(P22>=6,"Médio","Baixo")))
M23: =IF($A23="","",_xlfn.MAXIFS(Monitoramento!$B$2:$B$200,Monitoramento!$A$2:$A$200,$A23)) | N23: =IF(OR($A23="",M23=0),"",SUMIFS(Monitoramento!$D$2:$D$200,Monitoramento!$A$2:$A$200,$A23,Monitoramento!$B$2:$B$200,M23)) | O23: =IF(OR($A23="",M23=0),"",SUMIFS(Monitoramento!$E$2:$E$200,Monitoramento!$A$2:$A$200,$A23,Monitoramento!$B$2:$B$200,M23)) | P23: =IF(N23="","",N23*O23) | Q23: =IF(P23="","",IF(P23>=15,"Elevado",IF(P23>=6,"Médio","Baixo")))
M24: =IF($A24="","",_xlfn.MAXIFS(Monitoramento!$B$2:$B$200,Monitoramento!$A$2:$A$200,$A24)) | N24: =IF(OR($A24="",M24=0),"",SUMIFS(Monitoramento!$D$2:$D$200,Monitoramento!$A$2:$A$200,$A24,Monitoramento!$B$2:$B$200,M24)) | O24: =IF(OR($A24="",M24=0),"",SUMIFS(Monitoramento!$E$2:$E$200,Monitoramento!$A$2:$A$200,$A24,Monitoramento!$B$2:$B$200,M24)) | P24: =IF(N24="","",N24*O24) | Q24: =IF(P24="","",IF(P24>=15,"Elevado",IF(P24>=6,"Médio","Baixo")))
M25: =IF($A25="","",_xlfn.MAXIFS(Monitoramento!$B$2:$B$200,Monitoramento!$A$2:$A$200,$A25)) | N25: =IF(OR($A25="",M25=0),"",SUMIFS(Monitoramento!$D$2:$D$200,Monitoramento!$A$2:$A$200,$A25,Monitoramento!$B$2:$B$200,M25)) | O25: =IF(OR($A25="",M25=0),"",SUMIFS(Monitoramento!$E$2:$E$200,Monitoramento!$A$2:$A$200,$A25,Monitoramento!$B$2:$B$200,M25)) | P25: =IF(N25="","",N25*O25) | Q25: =IF(P25="","",IF(P25>=15,"Elevado",IF(P25>=6,"Médio","Baixo")))
M26: =IF($A26="","",_xlfn.MAXIFS(Monitoramento!$B$2:$B$200,Monitoramento!$A$2:$A$200,$A26)) | N26: =IF(OR($A26="",M26=0),"",SUMIFS(Monitoramento!$D$2:$D$200,Monitoramento!$A$2:$A$200,$A26,Monitoramento!$B$2:$B$200,M26)) | O26: =IF(OR($A26="",M26=0),"",SUMIFS(Monitoramento!$E$2:$E$200,Monitoramento!$A$2:$A$200,$A26,Monitoramento!$B$2:$B$200,M26)) | P26: =IF(N26="","",N26*O26) | Q26: =IF(P26="","",IF(P26>=15,"Elevado",IF(P26>=6,"Médio","Baixo")))
M27: =IF($A27="","",_xlfn.MAXIFS(Monitoramento!$B$2:$B$200,Monitoramento!$A$2:$A$200,$A27)) | N27: =IF(OR($A27="",M27=0),"",SUMIFS(Monitoramento!$D$2:$D$200,Monitoramento!$A$2:$A$200,$A27,Monitoramento!$B$2:$B$200,M27)) | O27: =IF(OR($A27="",M27=0),"",SUMIFS(Monitoramento!$E$2:$E$200,Monitoramento!$A$2:$A$200,$A27,Monitoramento!$B$2:$B$200,M27)) | P27: =IF(N27="","",N27*O27) | Q27: =IF(P27="","",IF(P27>=15,"Elevado",IF(P27>=6,"Médio","Baixo")))
... M200: =IF($A200="","",_xlfn.MAXIFS(Monitoramento!$B$2:$B$200,Monitoramento!$A$2:$A$200,$A200)) | N200: =IF(OR($A200="",M200=0),"",SUMIFS(Monitoramento!$D$2:$D$200,Monitoramento!$A$2:$A$200,$A200,Monitoramento!$B$2:$B$200,M200)) | O200: =IF(OR($A200="",M200=0),"",SUMIFS(Monitoramento!$E$2:$E$200,Monitoramento!$A$2:$A$200,$A200,Monitoramento!$B$2:$B$200,M200)) | P200: =IF(N200="","",N200*O200) | Q200: =IF(P200="","",IF(P200>=15,"Elevado",IF(P200>=6,"Médio","Baixo")))

Sheet Monitoramento
A1: ID do risco | B1: Sprint | C1: Data da revisão | D1: Probabilidade (1 a 5) | E1: Impacto (1 a 5) | F1: Exposição | G1: Nível | H1: Status | I1: Observação
A2: R01 | B2: 3 | C2: 46292 | D2: 4 | E2: 4 | F2: =IF(OR(D2="",E2=""),"",D2*E2) | G2: =IF(F2="","",IF(F2>=15,"Elevado",IF(F2>=6,"Médio","Baixo"))) | H2: Aberto | I2: Avaliação inicial (identificação dos riscos em 27/09, fim da sprint 3).
A3: R02 | B3: 3 | C3: 46292 | D3: 4 | E3: 5 | F3: =IF(OR(D3="",E3=""),"",D3*E3) | G3: =IF(F3="","",IF(F3>=15,"Elevado",IF(F3>=6,"Médio","Baixo"))) | H3: Aberto | I3: Avaliação inicial (identificação dos riscos em 27/09, fim da sprint 3).
A4: R03 | B4: 3 | C4: 46292 | D4: 4 | E4: 3 | F4: =IF(OR(D4="",E4=""),"",D4*E4) | G4: =IF(F4="","",IF(F4>=15,"Elevado",IF(F4>=6,"Médio","Baixo"))) | H4: Aberto | I4: Avaliação inicial (identificação dos riscos em 27/09, fim da sprint 3).
A5: R04 | B5: 3 | C5: 46292 | D5: 3 | E5: 3 | F5: =IF(OR(D5="",E5=""),"",D5*E5) | G5: =IF(F5="","",IF(F5>=15,"Elevado",IF(F5>=6,"Médio","Baixo"))) | H5: Aberto | I5: Avaliação inicial (identificação dos riscos em 27/09, fim da sprint 3).
A6: R05 | B6: 3 | C6: 46292 | D6: 3 | E6: 4 | F6: =IF(OR(D6="",E6=""),"",D6*E6) | G6: =IF(F6="","",IF(F6>=15,"Elevado",IF(F6>=6,"Médio","Baixo"))) | H6: Aberto | I6: Avaliação inicial (identificação dos riscos em 27/09, fim da sprint 3).
A7: R06 | B7: 3 | C7: 46292 | D7: 3 | E7: 3 | F7: =IF(OR(D7="",E7=""),"",D7*E7) | G7: =IF(F7="","",IF(F7>=15,"Elevado",IF(F7>=6,"Médio","Baixo"))) | H7: Em monitoramento | I7: Avaliação inicial (identificação dos riscos em 27/09, fim da sprint 3).
A8: R07 | B8: 3 | C8: 46292 | D8: 4 | E8: 3 | F8: =IF(OR(D8="",E8=""),"",D8*E8) | G8: =IF(F8="","",IF(F8>=15,"Elevado",IF(F8>=6,"Médio","Baixo"))) | H8: Aberto | I8: Avaliação inicial (identificação dos riscos em 27/09, fim da sprint 3).
A9: R08 | B9: 3 | C9: 46292 | D9: 4 | E9: 3 | F9: =IF(OR(D9="",E9=""),"",D9*E9) | G9: =IF(F9="","",IF(F9>=15,"Elevado",IF(F9>=6,"Médio","Baixo"))) | H9: Aberto | I9: Avaliação inicial (identificação dos riscos em 27/09, fim da sprint 3).
A10: R09 | B10: 3 | C10: 46292 | D10: 4 | E10: 3 | F10: =IF(OR(D10="",E10=""),"",D10*E10) | G10: =IF(F10="","",IF(F10>=15,"Elevado",IF(F10>=6,"Médio","Baixo"))) | H10: Aberto | I10: Avaliação inicial (identificação dos riscos em 27/09, fim da sprint 3).
A11: R10 | B11: 3 | C11: 46292 | D11: 5 | E11: 4 | F11: =IF(OR(D11="",E11=""),"",D11*E11) | G11: =IF(F11="","",IF(F11>=15,"Elevado",IF(F11>=6,"Médio","Baixo"))) | H11: Materializado | I11: Avaliação inicial (identificação dos riscos em 27/09, fim da sprint 3).
A12: R11 | B12: 3 | C12: 46292 | D12: 5 | E12: 3 | F12: =IF(OR(D12="",E12=""),"",D12*E12) | G12: =IF(F12="","",IF(F12>=15,"Elevado",IF(F12>=6,"Médio","Baixo"))) | H12: Aberto | I12: Avaliação inicial (identificação dos riscos em 27/09, fim da sprint 3).
A13: R12 | B13: 3 | C13: 46292 | D13: 4 | E13: 4 | F13: =IF(OR(D13="",E13=""),"",D13*E13) | G13: =IF(F13="","",IF(F13>=15,"Elevado",IF(F13>=6,"Médio","Baixo"))) | H13: Aberto | I13: Avaliação inicial (identificação dos riscos em 27/09, fim da sprint 3).
... A15: R14 | B15: 3 | C15: 46292 | D15: 4 | E15: 3 | F15: =IF(OR(D15="",E15=""),"",D15*E15) | G15: =IF(F15="","",IF(F15>=15,"Elevado",IF(F15>=6,"Médio","Baixo"))) | H15: Aberto | I15: Avaliação inicial (identificação dos riscos em 27/09, fim da sprint 3).
F16: =IF(OR(D16="",E16=""),"",D16*E16) | G16: =IF(F16="","",IF(F16>=15,"Elevado",IF(F16>=6,"Médio","Baixo")))
F17: =IF(OR(D17="",E17=""),"",D17*E17) | G17: =IF(F17="","",IF(F17>=15,"Elevado",IF(F17>=6,"Médio","Baixo")))
F18: =IF(OR(D18="",E18=""),"",D18*E18) | G18: =IF(F18="","",IF(F18>=15,"Elevado",IF(F18>=6,"Médio","Baixo")))
F19: =IF(OR(D19="",E19=""),"",D19*E19) | G19: =IF(F19="","",IF(F19>=15,"Elevado",IF(F19>=6,"Médio","Baixo")))
F20: =IF(OR(D20="",E20=""),"",D20*E20) | G20: =IF(F20="","",IF(F20>=15,"Elevado",IF(F20>=6,"Médio","Baixo")))
F21: =IF(OR(D21="",E21=""),"",D21*E21) | G21: =IF(F21="","",IF(F21>=15,"Elevado",IF(F21>=6,"Médio","Baixo")))
F22: =IF(OR(D22="",E22=""),"",D22*E22) | G22: =IF(F22="","",IF(F22>=15,"Elevado",IF(F22>=6,"Médio","Baixo")))
F23: =IF(OR(D23="",E23=""),"",D23*E23) | G23: =IF(F23="","",IF(F23>=15,"Elevado",IF(F23>=6,"Médio","Baixo")))
F24: =IF(OR(D24="",E24=""),"",D24*E24) | G24: =IF(F24="","",IF(F24>=15,"Elevado",IF(F24>=6,"Médio","Baixo")))
F25: =IF(OR(D25="",E25=""),"",D25*E25) | G25: =IF(F25="","",IF(F25>=15,"Elevado",IF(F25>=6,"Médio","Baixo")))
F26: =IF(OR(D26="",E26=""),"",D26*E26) | G26: =IF(F26="","",IF(F26>=15,"Elevado",IF(F26>=6,"Médio","Baixo")))
F27: =IF(OR(D27="",E27=""),"",D27*E27) | G27: =IF(F27="","",IF(F27>=15,"Elevado",IF(F27>=6,"Médio","Baixo")))
... F200: =IF(OR(D200="",E200=""),"",D200*E200) | G200: =IF(F200="","",IF(F200>=15,"Elevado",IF(F200>=6,"Médio","Baixo")))

Sheet Matriz
A1: Matriz de probabilidade × impacto (riscos não encerrados, última avaliação)
B3: Probabilidade →
B4: Impacto ↓ | C4: 1 | D4: 2 | E4: 3 | F4: 4 | G4: 5
B5: 5 | C5: =COUNTIFS(Riscos!$N$2:$N$200,1,Riscos!$O$2:$O$200,5,Riscos!$K$2:$K$200,"<>Encerrado") | D5: =COUNTIFS(Riscos!$N$2:$N$200,2,Riscos!$O$2:$O$200,5,Riscos!$K$2:$K$200,"<>Encerrado") | E5: =COUNTIFS(Riscos!$N$2:$N$200,3,Riscos!$O$2:$O$200,5,Riscos!$K$2:$K$200,"<>Encerrado") | F5: =COUNTIFS(Riscos!$N$2:$N$200,4,Riscos!$O$2:$O$200,5,Riscos!$K$2:$K$200,"<>Encerrado") | G5: =COUNTIFS(Riscos!$N$2:$N$200,5,Riscos!$O$2:$O$200,5,Riscos!$K$2:$K$200,"<>Encerrado")
B6: 4 | C6: =COUNTIFS(Riscos!$N$2:$N$200,1,Riscos!$O$2:$O$200,4,Riscos!$K$2:$K$200,"<>Encerrado") | D6: =COUNTIFS(Riscos!$N$2:$N$200,2,Riscos!$O$2:$O$200,4,Riscos!$K$2:$K$200,"<>Encerrado") | E6: =COUNTIFS(Riscos!$N$2:$N$200,3,Riscos!$O$2:$O$200,4,Riscos!$K$2:$K$200,"<>Encerrado") | F6: =COUNTIFS(Riscos!$N$2:$N$200,4,Riscos!$O$2:$O$200,4,Riscos!$K$2:$K$200,"<>Encerrado") | G6: =COUNTIFS(Riscos!$N$2:$N$200,5,Riscos!$O$2:$O$200,4,Riscos!$K$2:$K$200,"<>Encerrado")
B7: 3 | C7: =COUNTIFS(Riscos!$N$2:$N$200,1,Riscos!$O$2:$O$200,3,Riscos!$K$2:$K$200,"<>Encerrado") | D7: =COUNTIFS(Riscos!$N$2:$N$200,2,Riscos!$O$2:$O$200,3,Riscos!$K$2:$K$200,"<>Encerrado") | E7: =COUNTIFS(Riscos!$N$2:$N$200,3,Riscos!$O$2:$O$200,3,Riscos!$K$2:$K$200,"<>Encerrado") | F7: =COUNTIFS(Riscos!$N$2:$N$200,4,Riscos!$O$2:$O$200,3,Riscos!$K$2:$K$200,"<>Encerrado") | G7: =COUNTIFS(Riscos!$N$2:$N$200,5,Riscos!$O$2:$O$200,3,Riscos!$K$2:$K$200,"<>Encerrado")
B8: 2 | C8: =COUNTIFS(Riscos!$N$2:$N$200,1,Riscos!$O$2:$O$200,2,Riscos!$K$2:$K$200,"<>Encerrado") | D8: =COUNTIFS(Riscos!$N$2:$N$200,2,Riscos!$O$2:$O$200,2,Riscos!$K$2:$K$200,"<>Encerrado") | E8: =COUNTIFS(Riscos!$N$2:$N$200,3,Riscos!$O$2:$O$200,2,Riscos!$K$2:$K$200,"<>Encerrado") | F8: =COUNTIFS(Riscos!$N$2:$N$200,4,Riscos!$O$2:$O$200,2,Riscos!$K$2:$K$200,"<>Encerrado") | G8: =COUNTIFS(Riscos!$N$2:$N$200,5,Riscos!$O$2:$O$200,2,Riscos!$K$2:$K$200,"<>Encerrado")
B9: 1 | C9: =COUNTIFS(Riscos!$N$2:$N$200,1,Riscos!$O$2:$O$200,1,Riscos!$K$2:$K$200,"<>Encerrado") | D9: =COUNTIFS(Riscos!$N$2:$N$200,2,Riscos!$O$2:$O$200,1,Riscos!$K$2:$K$200,"<>Encerrado") | E9: =COUNTIFS(Riscos!$N$2:$N$200,3,Riscos!$O$2:$O$200,1,Riscos!$K$2:$K$200,"<>Encerrado") | F9: =COUNTIFS(Riscos!$N$2:$N$200,4,Riscos!$O$2:$O$200,1,Riscos!$K$2:$K$200,"<>Encerrado") | G9: =COUNTIFS(Riscos!$N$2:$N$200,5,Riscos!$O$2:$O$200,1,Riscos!$K$2:$K$200,"<>Encerrado")
B11: Cada célula conta os riscos com aquela probabilidade e impacto na última avaliação. Verde: baixo · amarelo: médio · vermelho: elevado.
B13: Riscos ativos | C13: =COUNTIFS(Riscos!$A$2:$A$200,"<>",Riscos!$K$2:$K$200,"<>Encerrado")
B14: Exposição elevada | C14: =COUNTIFS(Riscos!$P$2:$P$200,">=15",Riscos!$K$2:$K$200,"<>Encerrado")
B15: Materializados | C15: =COUNTIF(Riscos!$K$2:$K$200,"Materializado")

Sheet Decisões
A1: Data | B1: Sprint | C1: Tipo | D1: Indicador | E1: Contexto e dado | F1: Decisão | G1: Evidência | H1: Critério de sucesso | I1: Resultado | J1: Status
A2: 46292 | B2: 3 | C2: Gerencial | D2: Calendário de sprints | E2: Três calendários em uso (planilha antiga quinzenal com R1 até 04/10, Zenhub e página de Planejamento). Só o do Zenhub fecha nas datas das releases. | F2: Adotar o calendário do Zenhub como linha de base: R1 com 3 sprints, R2 com 4 e R3 com 5. | G2: Aba Sprints; Analytics/planilhas/sprints.csv; docs/planejamento/decisoes.mdx (D1) | H2: Todas as sprints até 29/11 criadas no Zenhub com as mesmas datas da planilha | J2: Vigente
A3: 46292 | B3: 3 | C3: Gerencial | D3: Velocity / pontos em Done | E3: Zenhub em 27/09: 0 pontos em Done na R1, issues sem estimativa e issues fechadas fora do Done. Mover uma issue fechada para o Done reabre a issue. | F3: Feito = issue fechada (Closed) ou no pipeline Done. Nunca mover issue fechada. Story points só em US, Task e Bug; Épicos, Sub-tasks e Task com Task filha não pontuam. | G3: Planilha Custos e AgileEVM (EVM - Valor Agregado, nota das colunas PP e PC); Analytics/src/gestao.py; docs/planejamento/decisoes.mdx (D2) | H3: Zero issues sem estimativa na conferência com o Zenhub a cada planning | I3: 27/09: 21 issues estimadas; nenhuma issue reaberta | J3: Vigente
A4: 46292 | B4: 3 | C4: Gerencial | D4: Custo (BAC e AC) | E4: EVM sem orçamento nem custo real: não havia custo/hora definido nem registro de horas; a disciplina exige horas reais. | F4: Usar o modelo de custo do aluno de 2026.1 (R$ 329,43 por integrante/semana; R$ 23,53/h). AC = custo planejado da sprint, trocado por horas × custo/hora quando o time registrar horas. | G4: Planilha Custos e AgileEVM (abas Custos, Planejamento e Horas); docs/planejamento/custos.mdx; decisoes.mdx (D3) | H4: 20 de 20 integrantes com horas na sprint 4 e CPI calculado no dashboard | J4: Planejada

Sheet Listas
A1: Categoria (EAR) | B1: Resposta | C1: Status do risco | D1: Tipo de decisão | E1: Status da decisão | F1: Integrantes
A2: Técnico | B2: Evitar | C2: Aberto | D2: Técnica | E2: Planejada | F2: Alexandre de Sanana Beck
A3: Gerencial | B3: Mitigar | C3: Em monitoramento | D3: Gerencial | E3: Vigente | F3: Antônio José Magalhães Leão Júnior
A4: Organizacional | B4: Transferir | C4: Materializado | E4: Concluída | F4: Daniel Ferreira Santos Rabelo
A5: Externo | B5: Aceitar | C5: Encerrado | E5: Revertida | F5: Diego Carlito Rodrigues de Souza
B6: Escalar | F6: Diogo Rodrigues Barboza
F7: Gabriel Marques de Souza
F8: Gabriel Moura
F9: Guilherme Storch
F10: Gustavo Roberto Silva de Melo
F11: Henrique Camelo Quenino
F12: Kathlyn Lara Murussi
F13: Lucas Bottino
F14: Luciano Freitas
F15: Luiza Maluf
F16: Manoel Felipe Teixeira Neto
F17: Marcos Antonio Teles de Castilhos
F18: Milena Fernandes Rocha
... F21: Wallyson Souza
